<?xml version="1.0" encoding="us-ascii"?>
<MQSim_Results>
	<Host>
		<Host.IO_Flow>
				 <Name>Host.IO_Flow.Synth.No_0</Name>
				 <Request_Count>405272</Request_Count>
				 <Read_Request_Count>405272</Read_Request_Count>
				 <Write_Request_Count>0</Write_Request_Count>
				 <IOPS>40526.455553</IOPS>
				 <IOPS_Read>40526.455553</IOPS_Read>
				 <IOPS_Write>0.000000</IOPS_Write>
				 <Bytes_Transferred>1659994112</Bytes_Transferred>
				 <Bytes_Transferred_Read>1659994112</Bytes_Transferred_Read>
				 <Bytes_Transferred_Write>0</Bytes_Transferred_Write>
				 <Bandwidth>165996361.946429</Bandwidth>
				 <Bandwidth_Read>165996361.946429</Bandwidth_Read>
				 <Bandwidth_Write>0.000000</Bandwidth_Write>
				 <Device_Response_Time>98</Device_Response_Time>
				 <Min_Device_Response_Time>88</Min_Device_Response_Time>
				 <Max_Device_Response_Time>350</Max_Device_Response_Time>
				 <End_to_End_Request_Delay>98</End_to_End_Request_Delay>
				 <Min_End_to_End_Request_Delay>88</Min_End_to_End_Request_Delay>
				 <Max_End_to_End_Request_Delay>350</Max_End_to_End_Request_Delay>
		</Host.IO_Flow>
	</Host>
	<SSDDevice>
		<SSDDevice.HostInterface>
				 <Name>SSDDevice.HostInterface</Name>
			<SSDDevice.IO_Stream>
					 <Stream_ID>0</Stream_ID>
					 <Average_Read_Transaction_Turnaround_Time>97</Average_Read_Transaction_Turnaround_Time>
					 <Average_Read_Transaction_Execution_Time>75</Average_Read_Transaction_Execution_Time>
					 <Average_Read_Transaction_Transfer_Time>12</Average_Read_Transaction_Transfer_Time>
					 <Average_Read_Transaction_Waiting_Time>9</Average_Read_Transaction_Waiting_Time>
					 <Average_Write_Transaction_Turnaround_Time>0</Average_Write_Transaction_Turnaround_Time>
					 <Average_Write_Transaction_Execution_Time>0</Average_Write_Transaction_Execution_Time>
					 <Average_Write_Transaction_Transfer_Time>0</Average_Write_Transaction_Transfer_Time>
					 <Average_Write_Transaction_Waiting_Time>0</Average_Write_Transaction_Waiting_Time>
			</SSDDevice.IO_Stream>
		</SSDDevice.HostInterface>
		<SSDDevice.FTL Issued_Flash_Read_CMD="405266" Issued_Flash_Interleaved_Read_CMD="0" Issued_Flash_Multiplane_Read_CMD="3" Issued_Flash_Copyback_Read_CMD="0" Issued_Flash_Multiplane_Copyback_Read_CMD="0" Issued_Flash_Program_CMD="0" Issued_Flash_Interleaved_Program_CMD="0" Issued_Flash_Multiplane_Program_CMD="0" Issued_Flash_Interleaved_Multiplane_Program_CMD="0" Issued_Flash_Copyback_Program_CMD="0" Issued_Flash_Multiplane_Copyback_Program_CMD="0" Issued_Flash_Erase_CMD="0" Issued_Flash_Interleaved_Erase_CMD="0" Issued_Flash_Multiplane_Erase_CMD="0" Issued_Flash_Interleaved_Multiplane_Erase_CMD="0" Issued_Flash_Suspend_Program_CMD="0" Issued_Flash_Suspend_Erase_CMD="0" Issued_Flash_Read_CMD_For_Mapping="0" Issued_Flash_Program_CMD_For_Mapping="0" CMT_Hits="405272" CMT_Hits_For_Read="405272" CMT_Hits_For_Write="0" CMT_Misses="0" CMT_Misses_For_Read="0" CMT_Misses_For_Write="0" Total_CMT_Queries="405272" Total_CMT_Queries_For_Reads="405272" Total_CMT_Queries_For_Writes="0" Total_GC_Executions="0" Average_Page_Movement_For_GC="nan" Total_WL_Executions="0" Average_Page_Movement_For_WL="nan"/>
		<SSDDevice.TSU>
			<SSDDevice.TSU.User_Read_TR_Queue Name="User_Read_TR_Queue@0@0" No_Of_Transactions_Enqueued="25282" No_Of_Transactions_Dequeued="25282" Avg_Queue_Length="0.022319" Max_Queue_Length="3" STDev_Queue_Length="0.037733" Avg_Transaction_Waiting_Time="8" Max_Transaction_Waiting_Time="184"/>
			<SSDDevice.TSU.User_Read_TR_Queue Name="User_Read_TR_Queue@0@1" No_Of_Transactions_Enqueued="25686" No_Of_Transactions_Dequeued="25686" Avg_Queue_Length="0.023649" Max_Queue_Length="3" STDev_Queue_Length="0.039904" Avg_Transaction_Waiting_Time="9" Max_Transaction_Waiting_Time="261"/>
			<SSDDevice.TSU.User_Read_TR_Queue Name="User_Read_TR_Queue@0@2" No_Of_Transactions_Enqueued="0" No_Of_Transactions_Dequeued="0" Avg_Queue_Length="0.000000" Max_Queue_Length="0" STDev_Queue_Length="0.000000" Avg_Transaction_Waiting_Time="9223372036854775808" Max_Transaction_Waiting_Time="0"/>
			<SSDDevice.TSU.User_Read_TR_Queue Name="User_Read_TR_Queue@0@3" No_Of_Transactions_Enqueued="0" No_Of_Transactions_Dequeued="0" Avg_Queue_Length="0.000000" Max_Queue_Length="0" STDev_Queue_Length="0.000000" Avg_Transaction_Waiting_Time="9223372036854775808" Max_Transaction_Waiting_Time="0"/>
			<SSDDevice.TSU.User_Read_TR_Queue Name="User_Read_TR_Queue@1@0" No_Of_Transactions_Enqueued="24985" No_Of_Transactions_Dequeued="24985" Avg_Queue_Length="0.021152" Max_Queue_Length="3" STDev_Queue_Length="0.035753" Avg_Transaction_Waiting_Time="8" Max_Transaction_Waiting_Time="197"/>
			<SSDDevice.TSU.User_Read_TR_Queue Name="User_Read_TR_Queue@1@1" No_Of_Transactions_Enqueued="25587" No_Of_Transactions_Dequeued="25587" Avg_Queue_Length="0.022612" Max_Queue_Length="3" STDev_Queue_Length="0.038236" Avg_Transaction_Waiting_Time="8" Max_Transaction_Waiting_Time="195"/>
			<SSDDevice.TSU.User_Read_TR_Queue Name="User_Read_TR_Queue@1@2" No_Of_Transactions_Enqueued="0" No_Of_Transactions_Dequeued="0" Avg_Queue_Length="0.000000" Max_Queue_Length="0" STDev_Queue_Length="0.000000" Avg_Transaction_Waiting_Time="9223372036854775808" Max_Transaction_Waiting_Time="0"/>
			<SSDDevice.TSU.User_Read_TR_Queue Name="User_Read_TR_Queue@1@3" No_Of_Transactions_Enqueued="0" No_Of_Transactions_Dequeued="0" Avg_Queue_Length="0.000000" Max_Queue_Length="0" STDev_Queue_Length="0.000000" Avg_Transaction_Waiting_Time="9223372036854775808" Max_Transaction_Waiting_Time="0"/>
			<SSDDevice.TSU.User_Read_TR_Queue Name="User_Read_TR_Queue@2@0" No_Of_Transactions_Enqueued="25181" No_Of_Transactions_Dequeued="25181" Avg_Queue_Length="0.022096" Max_Queue_Length="3" STDev_Queue_Length="0.037217" Avg_Transaction_Waiting_Time="8" Max_Transaction_Waiting_Time="186"/>
			<SSDDevice.TSU.User_Read_TR_Queue Name="User_Read_TR_Queue@2@1" No_Of_Transactions_Enqueued="25111" No_Of_Transactions_Dequeued="25111" Avg_Queue_Length="0.022023" Max_Queue_Length="3" STDev_Queue_Length="0.037081" Avg_Transaction_Waiting_Time="8" Max_Transaction_Waiting_Time="194"/>
			<SSDDevice.TSU.User_Read_TR_Queue Name="User_Read_TR_Queue@2@2" No_Of_Transactions_Enqueued="0" No_Of_Transactions_Dequeued="0" Avg_Queue_Length="0.000000" Max_Queue_Length="0" STDev_Queue_Length="0.000000" Avg_Transaction_Waiting_Time="9223372036854775808" Max_Transaction_Waiting_Time="0"/>
			<SSDDevice.TSU.User_Read_TR_Queue Name="User_Read_TR_Queue@2@3" No_Of_Transactions_Enqueued="0" No_Of_Transactions_Dequeued="0" Avg_Queue_Length="0.000000" Max_Queue_Length="0" STDev_Queue_Length="0.000000" Avg_Transaction_Waiting_Time="9223372036854775808" Max_Transaction_Waiting_Time="0"/>
			<SSDDevice.TSU.User_Read_TR_Queue Name="User_Read_TR_Queue@3@0" No_Of_Transactions_Enqueued="25373" No_Of_Transactions_Dequeued="25373" Avg_Queue_Length="0.021739" Max_Queue_Length="3" STDev_Queue_Length="0.036852" Avg_Transaction_Waiting_Time="8" Max_Transaction_Waiting_Time="182"/>
			<SSDDevice.TSU.User_Read_TR_Queue Name="User_Read_TR_Queue@3@1" No_Of_Transactions_Enqueued="25528" No_Of_Transactions_Dequeued="25528" Avg_Queue_Length="0.022933" Max_Queue_Length="3" STDev_Queue_Length="0.038685" Avg_Transaction_Waiting_Time="8" Max_Transaction_Waiting_Time="249"/>
			<SSDDevice.TSU.User_Read_TR_Queue Name="User_Read_TR_Queue@3@2" No_Of_Transactions_Enqueued="0" No_Of_Transactions_Dequeued="0" Avg_Queue_Length="0.000000" Max_Queue_Length="0" STDev_Queue_Length="0.000000" Avg_Transaction_Waiting_Time="9223372036854775808" Max_Transaction_Waiting_Time="0"/>
			<SSDDevice.TSU.User_Read_TR_Queue Name="User_Read_TR_Queue@3@3" No_Of_Transactions_Enqueued="0" No_Of_Transactions_Dequeued="0" Avg_Queue_Length="0.000000" Max_Queue_Length="0" STDev_Queue_Length="0.000000" Avg_Transaction_Waiting_Time="9223372036854775808" Max_Transaction_Waiting_Time="0"/>
			<SSDDevice.TSU.User_Read_TR_Queue Name="User_Read_TR_Queue@4@0" No_Of_Transactions_Enqueued="25450" No_Of_Transactions_Dequeued="25450" Avg_Queue_Length="0.022866" Max_Queue_Length="3" STDev_Queue_Length="0.038747" Avg_Transaction_Waiting_Time="8" Max_Transaction_Waiting_Time="187"/>
			<SSDDevice.TSU.User_Read_TR_Queue Name="User_Read_TR_Queue@4@1" No_Of_Transactions_Enqueued="25392" No_Of_Transactions_Dequeued="25392" Avg_Queue_Length="0.021980" Max_Queue_Length="3" STDev_Queue_Length="0.037181" Avg_Transaction_Waiting_Time="8" Max_Transaction_Waiting_Time="261"/>
			<SSDDevice.TSU.User_Read_TR_Queue Name="User_Read_TR_Queue@4@2" No_Of_Transactions_Enqueued="0" No_Of_Transactions_Dequeued="0" Avg_Queue_Length="0.000000" Max_Queue_Length="0" STDev_Queue_Length="0.000000" Avg_Transaction_Waiting_Time="9223372036854775808" Max_Transaction_Waiting_Time="0"/>
			<SSDDevice.TSU.User_Read_TR_Queue Name="User_Read_TR_Queue@4@3" No_Of_Transactions_Enqueued="0" No_Of_Transactions_Dequeued="0" Avg_Queue_Length="0.000000" Max_Queue_Length="0" STDev_Queue_Length="0.000000" Avg_Transaction_Waiting_Time="9223372036854775808" Max_Transaction_Waiting_Time="0"/>
			<SSDDevice.TSU.User_Read_TR_Queue Name="User_Read_TR_Queue@5@0" No_Of_Transactions_Enqueued="25260" No_Of_Transactions_Dequeued="25260" Avg_Queue_Length="0.021985" Max_Queue_Length="3" STDev_Queue_Length="0.037138" Avg_Transaction_Waiting_Time="8" Max_Transaction_Waiting_Time="195"/>
			<SSDDevice.TSU.User_Read_TR_Queue Name="User_Read_TR_Queue@5@1" No_Of_Transactions_Enqueued="25143" No_Of_Transactions_Dequeued="25143" Avg_Queue_Length="0.022207" Max_Queue_Length="3" STDev_Queue_Length="0.037487" Avg_Transaction_Waiting_Time="8" Max_Transaction_Waiting_Time="187"/>
			<SSDDevice.TSU.User_Read_TR_Queue Name="User_Read_TR_Queue@5@2" No_Of_Transactions_Enqueued="0" No_Of_Transactions_Dequeued="0" Avg_Queue_Length="0.000000" Max_Queue_Length="0" STDev_Queue_Length="0.000000" Avg_Transaction_Waiting_Time="9223372036854775808" Max_Transaction_Waiting_Time="0"/>
			<SSDDevice.TSU.User_Read_TR_Queue Name="User_Read_TR_Queue@5@3" No_Of_Transactions_Enqueued="0" No_Of_Transactions_Dequeued="0" Avg_Queue_Length="0.000000" Max_Queue_Length="0" STDev_Queue_Length="0.000000" Avg_Transaction_Waiting_Time="9223372036854775808" Max_Transaction_Waiting_Time="0"/>
			<SSDDevice.TSU.User_Read_TR_Queue Name="User_Read_TR_Queue@6@0" No_Of_Transactions_Enqueued="25412" No_Of_Transactions_Dequeued="25412" Avg_Queue_Length="0.023044" Max_Queue_Length="3" STDev_Queue_Length="0.038936" Avg_Transaction_Waiting_Time="9" Max_Transaction_Waiting_Time="186"/>
			<SSDDevice.TSU.User_Read_TR_Queue Name="User_Read_TR_Queue@6@1" No_Of_Transactions_Enqueued="25375" No_Of_Transactions_Dequeued="25375" Avg_Queue_Length="0.022972" Max_Queue_Length="3" STDev_Queue_Length="0.038628" Avg_Transaction_Waiting_Time="9" Max_Transaction_Waiting_Time="260"/>
			<SSDDevice.TSU.User_Read_TR_Queue Name="User_Read_TR_Queue@6@2" No_Of_Transactions_Enqueued="0" No_Of_Transactions_Dequeued="0" Avg_Queue_Length="0.000000" Max_Queue_Length="0" STDev_Queue_Length="0.000000" Avg_Transaction_Waiting_Time="9223372036854775808" Max_Transaction_Waiting_Time="0"/>
			<SSDDevice.TSU.User_Read_TR_Queue Name="User_Read_TR_Queue@6@3" No_Of_Transactions_Enqueued="0" No_Of_Transactions_Dequeued="0" Avg_Queue_Length="0.000000" Max_Queue_Length="0" STDev_Queue_Length="0.000000" Avg_Transaction_Waiting_Time="9223372036854775808" Max_Transaction_Waiting_Time="0"/>
			<SSDDevice.TSU.User_Read_TR_Queue Name="User_Read_TR_Queue@7@0" No_Of_Transactions_Enqueued="25224" No_Of_Transactions_Dequeued="25224" Avg_Queue_Length="0.022238" Max_Queue_Length="3" STDev_Queue_Length="0.037424" Avg_Transaction_Waiting_Time="8" Max_Transaction_Waiting_Time="251"/>
			<SSDDevice.TSU.User_Read_TR_Queue Name="User_Read_TR_Queue@7@1" No_Of_Transactions_Enqueued="25283" No_Of_Transactions_Dequeued="25283" Avg_Queue_Length="0.022170" Max_Queue_Length="3" STDev_Queue_Length="0.037508" Avg_Transaction_Waiting_Time="8" Max_Transaction_Waiting_Time="183"/>
			<SSDDevice.TSU.User_Read_TR_Queue Name="User_Read_TR_Queue@7@2" No_Of_Transactions_Enqueued="0" No_Of_Transactions_Dequeued="0" Avg_Queue_Length="0.000000" Max_Queue_Length="0" STDev_Queue_Length="0.000000" Avg_Transaction_Waiting_Time="9223372036854775808" Max_Transaction_Waiting_Time="0"/>
			<SSDDevice.TSU.User_Read_TR_Queue Name="User_Read_TR_Queue@7@3" No_Of_Transactions_Enqueued="0" No_Of_Transactions_Dequeued="0" Avg_Queue_Length="0.000000" Max_Queue_Length="0" STDev_Queue_Length="0.000000" Avg_Transaction_Waiting_Time="9223372036854775808" Max_Transaction_Waiting_Time="0"/>
			<SSDDevice.TSU.User_Write_TR_Queue Name="User_Write_TR_Queue@0@0" No_Of_Transactions_Enqueued="0" No_Of_Transactions_Dequeued="0" Avg_Queue_Length="0.000000" Max_Queue_Length="0" STDev_Queue_Length="0.000000" Avg_Transaction_Waiting_Time="9223372036854775808" Max_Transaction_Waiting_Time="0"/>
			<SSDDevice.TSU.User_Write_TR_Queue Name="User_Write_TR_Queue@0@1" No_Of_Transactions_Enqueued="0" No_Of_Transactions_Dequeued="0" Avg_Queue_Length="0.000000" Max_Queue_Length="0" STDev_Queue_Length="0.000000" Avg_Transaction_Waiting_Time="9223372036854775808" Max_Transaction_Waiting_Time="0"/>
			<SSDDevice.TSU.User_Write_TR_Queue Name="User_Write_TR_Queue@0@2" No_Of_Transactions_Enqueued="0" No_Of_Transactions_Dequeued="0" Avg_Queue_Length="0.000000" Max_Queue_Length="0" STDev_Queue_Length="0.000000" Avg_Transaction_Waiting_Time="9223372036854775808" Max_Transaction_Waiting_Time="0"/>
			<SSDDevice.TSU.User_Write_TR_Queue Name="User_Write_TR_Queue@0@3" No_Of_Transactions_Enqueued="0" No_Of_Transactions_Dequeued="0" Avg_Queue_Length="0.000000" Max_Queue_Length="0" STDev_Queue_Length="0.000000" Avg_Transaction_Waiting_Time="9223372036854775808" Max_Transaction_Waiting_Time="0"/>
			<SSDDevice.TSU.User_Write_TR_Queue Name="User_Write_TR_Queue@1@0" No_Of_Transactions_Enqueued="0" No_Of_Transactions_Dequeued="0" Avg_Queue_Length="0.000000" Max_Queue_Length="0" STDev_Queue_Length="0.000000" Avg_Transaction_Waiting_Time="9223372036854775808" Max_Transaction_Waiting_Time="0"/>
			<SSDDevice.TSU.User_Write_TR_Queue Name="User_Write_TR_Queue@1@1" No_Of_Transactions_Enqueued="0" No_Of_Transactions_Dequeued="0" Avg_Queue_Length="0.000000" Max_Queue_Length="0" STDev_Queue_Length="0.000000" Avg_Transaction_Waiting_Time="9223372036854775808" Max_Transaction_Waiting_Time="0"/>
			<SSDDevice.TSU.User_Write_TR_Queue Name="User_Write_TR_Queue@1@2" No_Of_Transactions_Enqueued="0" No_Of_Transactions_Dequeued="0" Avg_Queue_Length="0.000000" Max_Queue_Length="0" STDev_Queue_Length="0.000000" Avg_Transaction_Waiting_Time="9223372036854775808" Max_Transaction_Waiting_Time="0"/>
			<SSDDevice.TSU.User_Write_TR_Queue Name="User_Write_TR_Queue@1@3" No_Of_Transactions_Enqueued="0" No_Of_Transactions_Dequeued="0" Avg_Queue_Length="0.000000" Max_Queue_Length="0" STDev_Queue_Length="0.000000" Avg_Transaction_Waiting_Time="9223372036854775808" Max_Transaction_Waiting_Time="0"/>
			<SSDDevice.TSU.User_Write_TR_Queue Name="User_Write_TR_Queue@2@0" No_Of_Transactions_Enqueued="0" No_Of_Transactions_Dequeued="0" Avg_Queue_Length="0.000000" Max_Queue_Length="0" STDev_Queue_Length="0.000000" Avg_Transaction_Waiting_Time="9223372036854775808" Max_Transaction_Waiting_Time="0"/>
			<SSDDevice.TSU.User_Write_TR_Queue Name="User_Write_TR_Queue@2@1" No_Of_Transactions_Enqueued="0" No_Of_Transactions_Dequeued="0" Avg_Queue_Length="0.000000" Max_Queue_Length="0" STDev_Queue_Length="0.000000" Avg_Transaction_Waiting_Time="9223372036854775808" Max_Transaction_Waiting_Time="0"/>
			<SSDDevice.TSU.User_Write_TR_Queue Name="User_Write_TR_Queue@2@2" No_Of_Transactions_Enqueued="0" No_Of_Transactions_Dequeued="0" Avg_Queue_Length="0.000000" Max_Queue_Length="0" STDev_Queue_Length="0.000000" Avg_Transaction_Waiting_Time="9223372036854775808" Max_Transaction_Waiting_Time="0"/>
			<SSDDevice.TSU.User_Write_TR_Queue Name="User_Write_TR_Queue@2@3" No_Of_Transactions_Enqueued="0" No_Of_Transactions_Dequeued="0" Avg_Queue_Length="0.000000" Max_Queue_Length="0" STDev_Queue_Length="0.000000" Avg_Transaction_Waiting_Time="9223372036854775808" Max_Transaction_Waiting_Time="0"/>
			<SSDDevice.TSU.User_Write_TR_Queue Name="User_Write_TR_Queue@3@0" No_Of_Transactions_Enqueued="0" No_Of_Transactions_Dequeued="0" Avg_Queue_Length="0.000000" Max_Queue_Length="0" STDev_Queue_Length="0.000000" Avg_Transaction_Waiting_Time="9223372036854775808" Max_Transaction_Waiting_Time="0"/>
			<SSDDevice.TSU.User_Write_TR_Queue Name="User_Write_TR_Queue@3@1" No_Of_Transactions_Enqueued="0" No_Of_Transactions_Dequeued="0" Avg_Queue_Length="0.000000" Max_Queue_Length="0" STDev_Queue_Length="0.000000" Avg_Transaction_Waiting_Time="9223372036854775808" Max_Transaction_Waiting_Time="0"/>
			<SSDDevice.TSU.User_Write_TR_Queue Name="User_Write_TR_Queue@3@2" No_Of_Transactions_Enqueued="0" No_Of_Transactions_Dequeued="0" Avg_Queue_Length="0.000000" Max_Queue_Length="0" STDev_Queue_Length="0.000000" Avg_Transaction_Waiting_Time="9223372036854775808" Max_Transaction_Waiting_Time="0"/>
			<SSDDevice.TSU.User_Write_TR_Queue Name="User_Write_TR_Queue@3@3" No_Of_Transactions_Enqueued="0" No_Of_Transactions_Dequeued="0" Avg_Queue_Length="0.000000" Max_Queue_Length="0" STDev_Queue_Length="0.000000" Avg_Transaction_Waiting_Time="9223372036854775808" Max_Transaction_Waiting_Time="0"/>
			<SSDDevice.TSU.User_Write_TR_Queue Name="User_Write_TR_Queue@4@0" No_Of_Transactions_Enqueued="0" No_Of_Transactions_Dequeued="0" Avg_Queue_Length="0.000000" Max_Queue_Length="0" STDev_Queue_Length="0.000000" Avg_Transaction_Waiting_Time="9223372036854775808" Max_Transaction_Waiting_Time="0"/>
			<SSDDevice.TSU.User_Write_TR_Queue Name="User_Write_TR_Queue@4@1" No_Of_Transactions_Enqueued="0" No_Of_Transactions_Dequeued="0" Avg_Queue_Length="0.000000" Max_Queue_Length="0" STDev_Queue_Length="0.000000" Avg_Transaction_Waiting_Time="9223372036854775808" Max_Transaction_Waiting_Time="0"/>
			<SSDDevice.TSU.User_Write_TR_Queue Name="User_Write_TR_Queue@4@2" No_Of_Transactions_Enqueued="0" No_Of_Transactions_Dequeued="0" Avg_Queue_Length="0.000000" Max_Queue_Length="0" STDev_Queue_Length="0.000000" Avg_Transaction_Waiting_Time="9223372036854775808" Max_Transaction_Waiting_Time="0"/>
			<SSDDevice.TSU.User_Write_TR_Queue Name="User_Write_TR_Queue@4@3" No_Of_Transactions_Enqueued="0" No_Of_Transactions_Dequeued="0" Avg_Queue_Length="0.000000" Max_Queue_Length="0" STDev_Queue_Length="0.000000" Avg_Transaction_Waiting_Time="9223372036854775808" Max_Transaction_Waiting_Time="0"/>
			<SSDDevice.TSU.User_Write_TR_Queue Name="User_Write_TR_Queue@5@0" No_Of_Transactions_Enqueued="0" No_Of_Transactions_Dequeued="0" Avg_Queue_Length="0.000000" Max_Queue_Length="0" STDev_Queue_Length="0.000000" Avg_Transaction_Waiting_Time="9223372036854775808" Max_Transaction_Waiting_Time="0"/>
			<SSDDevice.TSU.User_Write_TR_Queue Name="User_Write_TR_Queue@5@1" No_Of_Transactions_Enqueued="0" No_Of_Transactions_Dequeued="0" Avg_Queue_Length="0.000000" Max_Queue_Length="0" STDev_Queue_Length="0.000000" Avg_Transaction_Waiting_Time="9223372036854775808" Max_Transaction_Waiting_Time="0"/>
			<SSDDevice.TSU.User_Write_TR_Queue Name="User_Write_TR_Queue@5@2" No_Of_Transactions_Enqueued="0" No_Of_Transactions_Dequeued="0" Avg_Queue_Length="0.000000" Max_Queue_Length="0" STDev_Queue_Length="0.000000" Avg_Transaction_Waiting_Time="9223372036854775808" Max_Transaction_Waiting_Time="0"/>
			<SSDDevice.TSU.User_Write_TR_Queue Name="User_Write_TR_Queue@5@3" No_Of_Transactions_Enqueued="0" No_Of_Transactions_Dequeued="0" Avg_Queue_Length="0.000000" Max_Queue_Length="0" STDev_Queue_Length="0.000000" Avg_Transaction_Waiting_Time="9223372036854775808" Max_Transaction_Waiting_Time="0"/>
			<SSDDevice.TSU.User_Write_TR_Queue Name="User_Write_TR_Queue@6@0" No_Of_Transactions_Enqueued="0" No_Of_Transactions_Dequeued="0" Avg_Queue_Length="0.000000" Max_Queue_Length="0" STDev_Queue_Length="0.000000" Avg_Transaction_Waiting_Time="9223372036854775808" Max_Transaction_Waiting_Time="0"/>
			<SSDDevice.TSU.User_Write_TR_Queue Name="User_Write_TR_Queue@6@1" No_Of_Transactions_Enqueued="0" No_Of_Transactions_Dequeued="0" Avg_Queue_Length="0.000000" Max_Queue_Length="0" STDev_Queue_Length="0.000000" Avg_Transaction_Waiting_Time="9223372036854775808" Max_Transaction_Waiting_Time="0"/>
			<SSDDevice.TSU.User_Write_TR_Queue Name="User_Write_TR_Queue@6@2" No_Of_Transactions_Enqueued="0" No_Of_Transactions_Dequeued="0" Avg_Queue_Length="0.000000" Max_Queue_Length="0" STDev_Queue_Length="0.000000" Avg_Transaction_Waiting_Time="9223372036854775808" Max_Transaction_Waiting_Time="0"/>
			<SSDDevice.TSU.User_Write_TR_Queue Name="User_Write_TR_Queue@6@3" No_Of_Transactions_Enqueued="0" No_Of_Transactions_Dequeued="0" Avg_Queue_Length="0.000000" Max_Queue_Length="0" STDev_Queue_Length="0.000000" Avg_Transaction_Waiting_Time="9223372036854775808" Max_Transaction_Waiting_Time="0"/>
			<SSDDevice.TSU.User_Write_TR_Queue Name="User_Write_TR_Queue@7@0" No_Of_Transactions_Enqueued="0" No_Of_Transactions_Dequeued="0" Avg_Queue_Length="0.000000" Max_Queue_Length="0" STDev_Queue_Length="0.000000" Avg_Transaction_Waiting_Time="9223372036854775808" Max_Transaction_Waiting_Time="0"/>
			<SSDDevice.TSU.User_Write_TR_Queue Name="User_Write_TR_Queue@7@1" No_Of_Transactions_Enqueued="0" No_Of_Transactions_Dequeued="0" Avg_Queue_Length="0.000000" Max_Queue_Length="0" STDev_Queue_Length="0.000000" Avg_Transaction_Waiting_Time="9223372036854775808" Max_Transaction_Waiting_Time="0"/>
			<SSDDevice.TSU.User_Write_TR_Queue Name="User_Write_TR_Queue@7@2" No_Of_Transactions_Enqueued="0" No_Of_Transactions_Dequeued="0" Avg_Queue_Length="0.000000" Max_Queue_Length="0" STDev_Queue_Length="0.000000" Avg_Transaction_Waiting_Time="9223372036854775808" Max_Transaction_Waiting_Time="0"/>
			<SSDDevice.TSU.User_Write_TR_Queue Name="User_Write_TR_Queue@7@3" No_Of_Transactions_Enqueued="0" No_Of_Transactions_Dequeued="0" Avg_Queue_Length="0.000000" Max_Queue_Length="0" STDev_Queue_Length="0.000000" Avg_Transaction_Waiting_Time="9223372036854775808" Max_Transaction_Waiting_Time="0"/>
			<SSDDevice.TSU.Mapping_Read_TR_Queue Name="Mapping_Read_TR_Queue@0@0" No_Of_Transactions_Enqueued="0" No_Of_Transactions_Dequeued="0" Avg_Queue_Length="0.000000" Max_Queue_Length="0" STDev_Queue_Length="0.000000" Avg_Transaction_Waiting_Time="9223372036854775808" Max_Transaction_Waiting_Time="0"/>
			<SSDDevice.TSU.Mapping_Read_TR_Queue Name="Mapping_Read_TR_Queue@0@1" No_Of_Transactions_Enqueued="0" No_Of_Transactions_Dequeued="0" Avg_Queue_Length="0.000000" Max_Queue_Length="0" STDev_Queue_Length="0.000000" Avg_Transaction_Waiting_Time="9223372036854775808" Max_Transaction_Waiting_Time="0"/>
			<SSDDevice.TSU.Mapping_Read_TR_Queue Name="Mapping_Read_TR_Queue@0@2" No_Of_Transactions_Enqueued="0" No_Of_Transactions_Dequeued="0" Avg_Queue_Length="0.000000" Max_Queue_Length="0" STDev_Queue_Length="0.000000" Avg_Transaction_Waiting_Time="9223372036854775808" Max_Transaction_Waiting_Time="0"/>
			<SSDDevice.TSU.Mapping_Read_TR_Queue Name="Mapping_Read_TR_Queue@0@3" No_Of_Transactions_Enqueued="0" No_Of_Transactions_Dequeued="0" Avg_Queue_Length="0.000000" Max_Queue_Length="0" STDev_Queue_Length="0.000000" Avg_Transaction_Waiting_Time="9223372036854775808" Max_Transaction_Waiting_Time="0"/>
			<SSDDevice.TSU.Mapping_Read_TR_Queue Name="Mapping_Read_TR_Queue@1@0" No_Of_Transactions_Enqueued="0" No_Of_Transactions_Dequeued="0" Avg_Queue_Length="0.000000" Max_Queue_Length="0" STDev_Queue_Length="0.000000" Avg_Transaction_Waiting_Time="9223372036854775808" Max_Transaction_Waiting_Time="0"/>
			<SSDDevice.TSU.Mapping_Read_TR_Queue Name="Mapping_Read_TR_Queue@1@1" No_Of_Transactions_Enqueued="0" No_Of_Transactions_Dequeued="0" Avg_Queue_Length="0.000000" Max_Queue_Length="0" STDev_Queue_Length="0.000000" Avg_Transaction_Waiting_Time="9223372036854775808" Max_Transaction_Waiting_Time="0"/>
			<SSDDevice.TSU.Mapping_Read_TR_Queue Name="Mapping_Read_TR_Queue@1@2" No_Of_Transactions_Enqueued="0" No_Of_Transactions_Dequeued="0" Avg_Queue_Length="0.000000" Max_Queue_Length="0" STDev_Queue_Length="0.000000" Avg_Transaction_Waiting_Time="9223372036854775808" Max_Transaction_Waiting_Time="0"/>
			<SSDDevice.TSU.Mapping_Read_TR_Queue Name="Mapping_Read_TR_Queue@1@3" No_Of_Transactions_Enqueued="0" No_Of_Transactions_Dequeued="0" Avg_Queue_Length="0.000000" Max_Queue_Length="0" STDev_Queue_Length="0.000000" Avg_Transaction_Waiting_Time="9223372036854775808" Max_Transaction_Waiting_Time="0"/>
			<SSDDevice.TSU.Mapping_Read_TR_Queue Name="Mapping_Read_TR_Queue@2@0" No_Of_Transactions_Enqueued="0" No_Of_Transactions_Dequeued="0" Avg_Queue_Length="0.000000" Max_Queue_Length="0" STDev_Queue_Length="0.000000" Avg_Transaction_Waiting_Time="9223372036854775808" Max_Transaction_Waiting_Time="0"/>
			<SSDDevice.TSU.Mapping_Read_TR_Queue Name="Mapping_Read_TR_Queue@2@1" No_Of_Transactions_Enqueued="0" No_Of_Transactions_Dequeued="0" Avg_Queue_Length="0.000000" Max_Queue_Length="0" STDev_Queue_Length="0.000000" Avg_Transaction_Waiting_Time="9223372036854775808" Max_Transaction_Waiting_Time="0"/>
			<SSDDevice.TSU.Mapping_Read_TR_Queue Name="Mapping_Read_TR_Queue@2@2" No_Of_Transactions_Enqueued="0" No_Of_Transactions_Dequeued="0" Avg_Queue_Length="0.000000" Max_Queue_Length="0" STDev_Queue_Length="0.000000" Avg_Transaction_Waiting_Time="9223372036854775808" Max_Transaction_Waiting_Time="0"/>
			<SSDDevice.TSU.Mapping_Read_TR_Queue Name="Mapping_Read_TR_Queue@2@3" No_Of_Transactions_Enqueued="0" No_Of_Transactions_Dequeued="0" Avg_Queue_Length="0.000000" Max_Queue_Length="0" STDev_Queue_Length="0.000000" Avg_Transaction_Waiting_Time="9223372036854775808" Max_Transaction_Waiting_Time="0"/>
			<SSDDevice.TSU.Mapping_Read_TR_Queue Name="Mapping_Read_TR_Queue@3@0" No_Of_Transactions_Enqueued="0" No_Of_Transactions_Dequeued="0" Avg_Queue_Length="0.000000" Max_Queue_Length="0" STDev_Queue_Length="0.000000" Avg_Transaction_Waiting_Time="9223372036854775808" Max_Transaction_Waiting_Time="0"/>
			<SSDDevice.TSU.Mapping_Read_TR_Queue Name="Mapping_Read_TR_Queue@3@1" No_Of_Transactions_Enqueued="0" No_Of_Transactions_Dequeued="0" Avg_Queue_Length="0.000000" Max_Queue_Length="0" STDev_Queue_Length="0.000000" Avg_Transaction_Waiting_Time="9223372036854775808" Max_Transaction_Waiting_Time="0"/>
			<SSDDevice.TSU.Mapping_Read_TR_Queue Name="Mapping_Read_TR_Queue@3@2" No_Of_Transactions_Enqueued="0" No_Of_Transactions_Dequeued="0" Avg_Queue_Length="0.000000" Max_Queue_Length="0" STDev_Queue_Length="0.000000" Avg_Transaction_Waiting_Time="9223372036854775808" Max_Transaction_Waiting_Time="0"/>
			<SSDDevice.TSU.Mapping_Read_TR_Queue Name="Mapping_Read_TR_Queue@3@3" No_Of_Transactions_Enqueued="0" No_Of_Transactions_Dequeued="0" Avg_Queue_Length="0.000000" Max_Queue_Length="0" STDev_Queue_Length="0.000000" Avg_Transaction_Waiting_Time="9223372036854775808" Max_Transaction_Waiting_Time="0"/>
			<SSDDevice.TSU.Mapping_Read_TR_Queue Name="Mapping_Read_TR_Queue@4@0" No_Of_Transactions_Enqueued="0" No_Of_Transactions_Dequeued="0" Avg_Queue_Length="0.000000" Max_Queue_Length="0" STDev_Queue_Length="0.000000" Avg_Transaction_Waiting_Time="9223372036854775808" Max_Transaction_Waiting_Time="0"/>
			<SSDDevice.TSU.Mapping_Read_TR_Queue Name="Mapping_Read_TR_Queue@4@1" No_Of_Transactions_Enqueued="0" No_Of_Transactions_Dequeued="0" Avg_Queue_Length="0.000000" Max_Queue_Length="0" STDev_Queue_Length="0.000000" Avg_Transaction_Waiting_Time="9223372036854775808" Max_Transaction_Waiting_Time="0"/>
			<SSDDevice.TSU.Mapping_Read_TR_Queue Name="Mapping_Read_TR_Queue@4@2" No_Of_Transactions_Enqueued="0" No_Of_Transactions_Dequeued="0" Avg_Queue_Length="0.000000" Max_Queue_Length="0" STDev_Queue_Length="0.000000" Avg_Transaction_Waiting_Time="9223372036854775808" Max_Transaction_Waiting_Time="0"/>
			<SSDDevice.TSU.Mapping_Read_TR_Queue Name="Mapping_Read_TR_Queue@4@3" No_Of_Transactions_Enqueued="0" No_Of_Transactions_Dequeued="0" Avg_Queue_Length="0.000000" Max_Queue_Length="0" STDev_Queue_Length="0.000000" Avg_Transaction_Waiting_Time="9223372036854775808" Max_Transaction_Waiting_Time="0"/>
			<SSDDevice.TSU.Mapping_Read_TR_Queue Name="Mapping_Read_TR_Queue@5@0" No_Of_Transactions_Enqueued="0" No_Of_Transactions_Dequeued="0" Avg_Queue_Length="0.000000" Max_Queue_Length="0" STDev_Queue_Length="0.000000" Avg_Transaction_Waiting_Time="9223372036854775808" Max_Transaction_Waiting_Time="0"/>
			<SSDDevice.TSU.Mapping_Read_TR_Queue Name="Mapping_Read_TR_Queue@5@1" No_Of_Transactions_Enqueued="0" No_Of_Transactions_Dequeued="0" Avg_Queue_Length="0.000000" Max_Queue_Length="0" STDev_Queue_Length="0.000000" Avg_Transaction_Waiting_Time="9223372036854775808" Max_Transaction_Waiting_Time="0"/>
			<SSDDevice.TSU.Mapping_Read_TR_Queue Name="Mapping_Read_TR_Queue@5@2" No_Of_Transactions_Enqueued="0" No_Of_Transactions_Dequeued="0" Avg_Queue_Length="0.000000" Max_Queue_Length="0" STDev_Queue_Length="0.000000" Avg_Transaction_Waiting_Time="9223372036854775808" Max_Transaction_Waiting_Time="0"/>
			<SSDDevice.TSU.Mapping_Read_TR_Queue Name="Mapping_Read_TR_Queue@5@3" No_Of_Transactions_Enqueued="0" No_Of_Transactions_Dequeued="0" Avg_Queue_Length="0.000000" Max_Queue_Length="0" STDev_Queue_Length="0.000000" Avg_Transaction_Waiting_Time="9223372036854775808" Max_Transaction_Waiting_Time="0"/>
			<SSDDevice.TSU.Mapping_Read_TR_Queue Name="Mapping_Read_TR_Queue@6@0" No_Of_Transactions_Enqueued="0" No_Of_Transactions_Dequeued="0" Avg_Queue_Length="0.000000" Max_Queue_Length="0" STDev_Queue_Length="0.000000" Avg_Transaction_Waiting_Time="9223372036854775808" Max_Transaction_Waiting_Time="0"/>
			<SSDDevice.TSU.Mapping_Read_TR_Queue Name="Mapping_Read_TR_Queue@6@1" No_Of_Transactions_Enqueued="0" No_Of_Transactions_Dequeued="0" Avg_Queue_Length="0.000000" Max_Queue_Length="0" STDev_Queue_Length="0.000000" Avg_Transaction_Waiting_Time="9223372036854775808" Max_Transaction_Waiting_Time="0"/>
			<SSDDevice.TSU.Mapping_Read_TR_Queue Name="Mapping_Read_TR_Queue@6@2" No_Of_Transactions_Enqueued="0" No_Of_Transactions_Dequeued="0" Avg_Queue_Length="0.000000" Max_Queue_Length="0" STDev_Queue_Length="0.000000" Avg_Transaction_Waiting_Time="9223372036854775808" Max_Transaction_Waiting_Time="0"/>
			<SSDDevice.TSU.Mapping_Read_TR_Queue Name="Mapping_Read_TR_Queue@6@3" No_Of_Transactions_Enqueued="0" No_Of_Transactions_Dequeued="0" Avg_Queue_Length="0.000000" Max_Queue_Length="0" STDev_Queue_Length="0.000000" Avg_Transaction_Waiting_Time="9223372036854775808" Max_Transaction_Waiting_Time="0"/>
			<SSDDevice.TSU.Mapping_Read_TR_Queue Name="Mapping_Read_TR_Queue@7@0" No_Of_Transactions_Enqueued="0" No_Of_Transactions_Dequeued="0" Avg_Queue_Length="0.000000" Max_Queue_Length="0" STDev_Queue_Length="0.000000" Avg_Transaction_Waiting_Time="9223372036854775808" Max_Transaction_Waiting_Time="0"/>
			<SSDDevice.TSU.Mapping_Read_TR_Queue Name="Mapping_Read_TR_Queue@7@1" No_Of_Transactions_Enqueued="0" No_Of_Transactions_Dequeued="0" Avg_Queue_Length="0.000000" Max_Queue_Length="0" STDev_Queue_Length="0.000000" Avg_Transaction_Waiting_Time="9223372036854775808" Max_Transaction_Waiting_Time="0"/>
			<SSDDevice.TSU.Mapping_Read_TR_Queue Name="Mapping_Read_TR_Queue@7@2" No_Of_Transactions_Enqueued="0" No_Of_Transactions_Dequeued="0" Avg_Queue_Length="0.000000" Max_Queue_Length="0" STDev_Queue_Length="0.000000" Avg_Transaction_Waiting_Time="9223372036854775808" Max_Transaction_Waiting_Time="0"/>
			<SSDDevice.TSU.Mapping_Read_TR_Queue Name="Mapping_Read_TR_Queue@7@3" No_Of_Transactions_Enqueued="0" No_Of_Transactions_Dequeued="0" Avg_Queue_Length="0.000000" Max_Queue_Length="0" STDev_Queue_Length="0.000000" Avg_Transaction_Waiting_Time="9223372036854775808" Max_Transaction_Waiting_Time="0"/>
			<SSDDevice.TSU.Mapping_Write_TR_Queue Name="Mapping_Write_TR_Queue@0@0" No_Of_Transactions_Enqueued="0" No_Of_Transactions_Dequeued="0" Avg_Queue_Length="0.000000" Max_Queue_Length="0" STDev_Queue_Length="0.000000" Avg_Transaction_Waiting_Time="9223372036854775808" Max_Transaction_Waiting_Time="0"/>
			<SSDDevice.TSU.Mapping_Write_TR_Queue Name="Mapping_Write_TR_Queue@0@1" No_Of_Transactions_Enqueued="0" No_Of_Transactions_Dequeued="0" Avg_Queue_Length="0.000000" Max_Queue_Length="0" STDev_Queue_Length="0.000000" Avg_Transaction_Waiting_Time="9223372036854775808" Max_Transaction_Waiting_Time="0"/>
			<SSDDevice.TSU.Mapping_Write_TR_Queue Name="Mapping_Write_TR_Queue@0@2" No_Of_Transactions_Enqueued="0" No_Of_Transactions_Dequeued="0" Avg_Queue_Length="0.000000" Max_Queue_Length="0" STDev_Queue_Length="0.000000" Avg_Transaction_Waiting_Time="9223372036854775808" Max_Transaction_Waiting_Time="0"/>
			<SSDDevice.TSU.Mapping_Write_TR_Queue Name="Mapping_Write_TR_Queue@0@3" No_Of_Transactions_Enqueued="0" No_Of_Transactions_Dequeued="0" Avg_Queue_Length="0.000000" Max_Queue_Length="0" STDev_Queue_Length="0.000000" Avg_Transaction_Waiting_Time="9223372036854775808" Max_Transaction_Waiting_Time="0"/>
			<SSDDevice.TSU.Mapping_Write_TR_Queue Name="Mapping_Write_TR_Queue@1@0" No_Of_Transactions_Enqueued="0" No_Of_Transactions_Dequeued="0" Avg_Queue_Length="0.000000" Max_Queue_Length="0" STDev_Queue_Length="0.000000" Avg_Transaction_Waiting_Time="9223372036854775808" Max_Transaction_Waiting_Time="0"/>
			<SSDDevice.TSU.Mapping_Write_TR_Queue Name="Mapping_Write_TR_Queue@1@1" No_Of_Transactions_Enqueued="0" No_Of_Transactions_Dequeued="0" Avg_Queue_Length="0.000000" Max_Queue_Length="0" STDev_Queue_Length="0.000000" Avg_Transaction_Waiting_Time="9223372036854775808" Max_Transaction_Waiting_Time="0"/>
			<SSDDevice.TSU.Mapping_Write_TR_Queue Name="Mapping_Write_TR_Queue@1@2" No_Of_Transactions_Enqueued="0" No_Of_Transactions_Dequeued="0" Avg_Queue_Length="0.000000" Max_Queue_Length="0" STDev_Queue_Length="0.000000" Avg_Transaction_Waiting_Time="9223372036854775808" Max_Transaction_Waiting_Time="0"/>
			<SSDDevice.TSU.Mapping_Write_TR_Queue Name="Mapping_Write_TR_Queue@1@3" No_Of_Transactions_Enqueued="0" No_Of_Transactions_Dequeued="0" Avg_Queue_Length="0.000000" Max_Queue_Length="0" STDev_Queue_Length="0.000000" Avg_Transaction_Waiting_Time="9223372036854775808" Max_Transaction_Waiting_Time="0"/>
			<SSDDevice.TSU.Mapping_Write_TR_Queue Name="Mapping_Write_TR_Queue@2@0" No_Of_Transactions_Enqueued="0" No_Of_Transactions_Dequeued="0" Avg_Queue_Length="0.000000" Max_Queue_Length="0" STDev_Queue_Length="0.000000" Avg_Transaction_Waiting_Time="9223372036854775808" Max_Transaction_Waiting_Time="0"/>
			<SSDDevice.TSU.Mapping_Write_TR_Queue Name="Mapping_Write_TR_Queue@2@1" No_Of_Transactions_Enqueued="0" No_Of_Transactions_Dequeued="0" Avg_Queue_Length="0.000000" Max_Queue_Length="0" STDev_Queue_Length="0.000000" Avg_Transaction_Waiting_Time="9223372036854775808" Max_Transaction_Waiting_Time="0"/>
			<SSDDevice.TSU.Mapping_Write_TR_Queue Name="Mapping_Write_TR_Queue@2@2" No_Of_Transactions_Enqueued="0" No_Of_Transactions_Dequeued="0" Avg_Queue_Length="0.000000" Max_Queue_Length="0" STDev_Queue_Length="0.000000" Avg_Transaction_Waiting_Time="9223372036854775808" Max_Transaction_Waiting_Time="0"/>
			<SSDDevice.TSU.Mapping_Write_TR_Queue Name="Mapping_Write_TR_Queue@2@3" No_Of_Transactions_Enqueued="0" No_Of_Transactions_Dequeued="0" Avg_Queue_Length="0.000000" Max_Queue_Length="0" STDev_Queue_Length="0.000000" Avg_Transaction_Waiting_Time="9223372036854775808" Max_Transaction_Waiting_Time="0"/>
			<SSDDevice.TSU.Mapping_Write_TR_Queue Name="Mapping_Write_TR_Queue@3@0" No_Of_Transactions_Enqueued="0" No_Of_Transactions_Dequeued="0" Avg_Queue_Length="0.000000" Max_Queue_Length="0" STDev_Queue_Length="0.000000" Avg_Transaction_Waiting_Time="9223372036854775808" Max_Transaction_Waiting_Time="0"/>
			<SSDDevice.TSU.Mapping_Write_TR_Queue Name="Mapping_Write_TR_Queue@3@1" No_Of_Transactions_Enqueued="0" No_Of_Transactions_Dequeued="0" Avg_Queue_Length="0.000000" Max_Queue_Length="0" STDev_Queue_Length="0.000000" Avg_Transaction_Waiting_Time="9223372036854775808" Max_Transaction_Waiting_Time="0"/>
			<SSDDevice.TSU.Mapping_Write_TR_Queue Name="Mapping_Write_TR_Queue@3@2" No_Of_Transactions_Enqueued="0" No_Of_Transactions_Dequeued="0" Avg_Queue_Length="0.000000" Max_Queue_Length="0" STDev_Queue_Length="0.000000" Avg_Transaction_Waiting_Time="9223372036854775808" Max_Transaction_Waiting_Time="0"/>
			<SSDDevice.TSU.Mapping_Write_TR_Queue Name="Mapping_Write_TR_Queue@3@3" No_Of_Transactions_Enqueued="0" No_Of_Transactions_Dequeued="0" Avg_Queue_Length="0.000000" Max_Queue_Length="0" STDev_Queue_Length="0.000000" Avg_Transaction_Waiting_Time="9223372036854775808" Max_Transaction_Waiting_Time="0"/>
			<SSDDevice.TSU.Mapping_Write_TR_Queue Name="Mapping_Write_TR_Queue@4@0" No_Of_Transactions_Enqueued="0" No_Of_Transactions_Dequeued="0" Avg_Queue_Length="0.000000" Max_Queue_Length="0" STDev_Queue_Length="0.000000" Avg_Transaction_Waiting_Time="9223372036854775808" Max_Transaction_Waiting_Time="0"/>
			<SSDDevice.TSU.Mapping_Write_TR_Queue Name="Mapping_Write_TR_Queue@4@1" No_Of_Transactions_Enqueued="0" No_Of_Transactions_Dequeued="0" Avg_Queue_Length="0.000000" Max_Queue_Length="0" STDev_Queue_Length="0.000000" Avg_Transaction_Waiting_Time="9223372036854775808" Max_Transaction_Waiting_Time="0"/>
			<SSDDevice.TSU.Mapping_Write_TR_Queue Name="Mapping_Write_TR_Queue@4@2" No_Of_Transactions_Enqueued="0" No_Of_Transactions_Dequeued="0" Avg_Queue_Length="0.000000" Max_Queue_Length="0" STDev_Queue_Length="0.000000" Avg_Transaction_Waiting_Time="9223372036854775808" Max_Transaction_Waiting_Time="0"/>
			<SSDDevice.TSU.Mapping_Write_TR_Queue Name="Mapping_Write_TR_Queue@4@3" No_Of_Transactions_Enqueued="0" No_Of_Transactions_Dequeued="0" Avg_Queue_Length="0.000000" Max_Queue_Length="0" STDev_Queue_Length="0.000000" Avg_Transaction_Waiting_Time="9223372036854775808" Max_Transaction_Waiting_Time="0"/>
			<SSDDevice.TSU.Mapping_Write_TR_Queue Name="Mapping_Write_TR_Queue@5@0" No_Of_Transactions_Enqueued="0" No_Of_Transactions_Dequeued="0" Avg_Queue_Length="0.000000" Max_Queue_Length="0" STDev_Queue_Length="0.000000" Avg_Transaction_Waiting_Time="9223372036854775808" Max_Transaction_Waiting_Time="0"/>
			<SSDDevice.TSU.Mapping_Write_TR_Queue Name="Mapping_Write_TR_Queue@5@1" No_Of_Transactions_Enqueued="0" No_Of_Transactions_Dequeued="0" Avg_Queue_Length="0.000000" Max_Queue_Length="0" STDev_Queue_Length="0.000000" Avg_Transaction_Waiting_Time="9223372036854775808" Max_Transaction_Waiting_Time="0"/>
			<SSDDevice.TSU.Mapping_Write_TR_Queue Name="Mapping_Write_TR_Queue@5@2" No_Of_Transactions_Enqueued="0" No_Of_Transactions_Dequeued="0" Avg_Queue_Length="0.000000" Max_Queue_Length="0" STDev_Queue_Length="0.000000" Avg_Transaction_Waiting_Time="9223372036854775808" Max_Transaction_Waiting_Time="0"/>
			<SSDDevice.TSU.Mapping_Write_TR_Queue Name="Mapping_Write_TR_Queue@5@3" No_Of_Transactions_Enqueued="0" No_Of_Transactions_Dequeued="0" Avg_Queue_Length="0.000000" Max_Queue_Length="0" STDev_Queue_Length="0.000000" Avg_Transaction_Waiting_Time="9223372036854775808" Max_Transaction_Waiting_Time="0"/>
			<SSDDevice.TSU.Mapping_Write_TR_Queue Name="Mapping_Write_TR_Queue@6@0" No_Of_Transactions_Enqueued="0" No_Of_Transactions_Dequeued="0" Avg_Queue_Length="0.000000" Max_Queue_Length="0" STDev_Queue_Length="0.000000" Avg_Transaction_Waiting_Time="9223372036854775808" Max_Transaction_Waiting_Time="0"/>
			<SSDDevice.TSU.Mapping_Write_TR_Queue Name="Mapping_Write_TR_Queue@6@1" No_Of_Transactions_Enqueued="0" No_Of_Transactions_Dequeued="0" Avg_Queue_Length="0.000000" Max_Queue_Length="0" STDev_Queue_Length="0.000000" Avg_Transaction_Waiting_Time="9223372036854775808" Max_Transaction_Waiting_Time="0"/>
			<SSDDevice.TSU.Mapping_Write_TR_Queue Name="Mapping_Write_TR_Queue@6@2" No_Of_Transactions_Enqueued="0" No_Of_Transactions_Dequeued="0" Avg_Queue_Length="0.000000" Max_Queue_Length="0" STDev_Queue_Length="0.000000" Avg_Transaction_Waiting_Time="9223372036854775808" Max_Transaction_Waiting_Time="0"/>
			<SSDDevice.TSU.Mapping_Write_TR_Queue Name="Mapping_Write_TR_Queue@6@3" No_Of_Transactions_Enqueued="0" No_Of_Transactions_Dequeued="0" Avg_Queue_Length="0.000000" Max_Queue_Length="0" STDev_Queue_Length="0.000000" Avg_Transaction_Waiting_Time="9223372036854775808" Max_Transaction_Waiting_Time="0"/>
			<SSDDevice.TSU.Mapping_Write_TR_Queue Name="Mapping_Write_TR_Queue@7@0" No_Of_Transactions_Enqueued="0" No_Of_Transactions_Dequeued="0" Avg_Queue_Length="0.000000" Max_Queue_Length="0" STDev_Queue_Length="0.000000" Avg_Transaction_Waiting_Time="9223372036854775808" Max_Transaction_Waiting_Time="0"/>
			<SSDDevice.TSU.Mapping_Write_TR_Queue Name="Mapping_Write_TR_Queue@7@1" No_Of_Transactions_Enqueued="0" No_Of_Transactions_Dequeued="0" Avg_Queue_Length="0.000000" Max_Queue_Length="0" STDev_Queue_Length="0.000000" Avg_Transaction_Waiting_Time="9223372036854775808" Max_Transaction_Waiting_Time="0"/>
			<SSDDevice.TSU.Mapping_Write_TR_Queue Name="Mapping_Write_TR_Queue@7@2" No_Of_Transactions_Enqueued="0" No_Of_Transactions_Dequeued="0" Avg_Queue_Length="0.000000" Max_Queue_Length="0" STDev_Queue_Length="0.000000" Avg_Transaction_Waiting_Time="9223372036854775808" Max_Transaction_Waiting_Time="0"/>
			<SSDDevice.TSU.Mapping_Write_TR_Queue Name="Mapping_Write_TR_Queue@7@3" No_Of_Transactions_Enqueued="0" No_Of_Transactions_Dequeued="0" Avg_Queue_Length="0.000000" Max_Queue_Length="0" STDev_Queue_Length="0.000000" Avg_Transaction_Waiting_Time="9223372036854775808" Max_Transaction_Waiting_Time="0"/>
			<SSDDevice.TSU.GC_Read_TR_Queue Name="GC_Read_TR_Queue@0@0" No_Of_Transactions_Enqueued="0" No_Of_Transactions_Dequeued="0" Avg_Queue_Length="0.000000" Max_Queue_Length="0" STDev_Queue_Length="0.000000" Avg_Transaction_Waiting_Time="9223372036854775808" Max_Transaction_Waiting_Time="0"/>
			<SSDDevice.TSU.GC_Read_TR_Queue Name="GC_Read_TR_Queue@0@1" No_Of_Transactions_Enqueued="0" No_Of_Transactions_Dequeued="0" Avg_Queue_Length="0.000000" Max_Queue_Length="0" STDev_Queue_Length="0.000000" Avg_Transaction_Waiting_Time="9223372036854775808" Max_Transaction_Waiting_Time="0"/>
			<SSDDevice.TSU.GC_Read_TR_Queue Name="GC_Read_TR_Queue@0@2" No_Of_Transactions_Enqueued="0" No_Of_Transactions_Dequeued="0" Avg_Queue_Length="0.000000" Max_Queue_Length="0" STDev_Queue_Length="0.000000" Avg_Transaction_Waiting_Time="9223372036854775808" Max_Transaction_Waiting_Time="0"/>
			<SSDDevice.TSU.GC_Read_TR_Queue Name="GC_Read_TR_Queue@0@3" No_Of_Transactions_Enqueued="0" No_Of_Transactions_Dequeued="0" Avg_Queue_Length="0.000000" Max_Queue_Length="0" STDev_Queue_Length="0.000000" Avg_Transaction_Waiting_Time="9223372036854775808" Max_Transaction_Waiting_Time="0"/>
			<SSDDevice.TSU.GC_Read_TR_Queue Name="GC_Read_TR_Queue@1@0" No_Of_Transactions_Enqueued="0" No_Of_Transactions_Dequeued="0" Avg_Queue_Length="0.000000" Max_Queue_Length="0" STDev_Queue_Length="0.000000" Avg_Transaction_Waiting_Time="9223372036854775808" Max_Transaction_Waiting_Time="0"/>
			<SSDDevice.TSU.GC_Read_TR_Queue Name="GC_Read_TR_Queue@1@1" No_Of_Transactions_Enqueued="0" No_Of_Transactions_Dequeued="0" Avg_Queue_Length="0.000000" Max_Queue_Length="0" STDev_Queue_Length="0.000000" Avg_Transaction_Waiting_Time="9223372036854775808" Max_Transaction_Waiting_Time="0"/>
			<SSDDevice.TSU.GC_Read_TR_Queue Name="GC_Read_TR_Queue@1@2" No_Of_Transactions_Enqueued="0" No_Of_Transactions_Dequeued="0" Avg_Queue_Length="0.000000" Max_Queue_Length="0" STDev_Queue_Length="0.000000" Avg_Transaction_Waiting_Time="9223372036854775808" Max_Transaction_Waiting_Time="0"/>
			<SSDDevice.TSU.GC_Read_TR_Queue Name="GC_Read_TR_Queue@1@3" No_Of_Transactions_Enqueued="0" No_Of_Transactions_Dequeued="0" Avg_Queue_Length="0.000000" Max_Queue_Length="0" STDev_Queue_Length="0.000000" Avg_Transaction_Waiting_Time="9223372036854775808" Max_Transaction_Waiting_Time="0"/>
			<SSDDevice.TSU.GC_Read_TR_Queue Name="GC_Read_TR_Queue@2@0" No_Of_Transactions_Enqueued="0" No_Of_Transactions_Dequeued="0" Avg_Queue_Length="0.000000" Max_Queue_Length="0" STDev_Queue_Length="0.000000" Avg_Transaction_Waiting_Time="9223372036854775808" Max_Transaction_Waiting_Time="0"/>
			<SSDDevice.TSU.GC_Read_TR_Queue Name="GC_Read_TR_Queue@2@1" No_Of_Transactions_Enqueued="0" No_Of_Transactions_Dequeued="0" Avg_Queue_Length="0.000000" Max_Queue_Length="0" STDev_Queue_Length="0.000000" Avg_Transaction_Waiting_Time="9223372036854775808" Max_Transaction_Waiting_Time="0"/>
			<SSDDevice.TSU.GC_Read_TR_Queue Name="GC_Read_TR_Queue@2@2" No_Of_Transactions_Enqueued="0" No_Of_Transactions_Dequeued="0" Avg_Queue_Length="0.000000" Max_Queue_Length="0" STDev_Queue_Length="0.000000" Avg_Transaction_Waiting_Time="9223372036854775808" Max_Transaction_Waiting_Time="0"/>
			<SSDDevice.TSU.GC_Read_TR_Queue Name="GC_Read_TR_Queue@2@3" No_Of_Transactions_Enqueued="0" No_Of_Transactions_Dequeued="0" Avg_Queue_Length="0.000000" Max_Queue_Length="0" STDev_Queue_Length="0.000000" Avg_Transaction_Waiting_Time="9223372036854775808" Max_Transaction_Waiting_Time="0"/>
			<SSDDevice.TSU.GC_Read_TR_Queue Name="GC_Read_TR_Queue@3@0" No_Of_Transactions_Enqueued="0" No_Of_Transactions_Dequeued="0" Avg_Queue_Length="0.000000" Max_Queue_Length="0" STDev_Queue_Length="0.000000" Avg_Transaction_Waiting_Time="9223372036854775808" Max_Transaction_Waiting_Time="0"/>
			<SSDDevice.TSU.GC_Read_TR_Queue Name="GC_Read_TR_Queue@3@1" No_Of_Transactions_Enqueued="0" No_Of_Transactions_Dequeued="0" Avg_Queue_Length="0.000000" Max_Queue_Length="0" STDev_Queue_Length="0.000000" Avg_Transaction_Waiting_Time="9223372036854775808" Max_Transaction_Waiting_Time="0"/>
			<SSDDevice.TSU.GC_Read_TR_Queue Name="GC_Read_TR_Queue@3@2" No_Of_Transactions_Enqueued="0" No_Of_Transactions_Dequeued="0" Avg_Queue_Length="0.000000" Max_Queue_Length="0" STDev_Queue_Length="0.000000" Avg_Transaction_Waiting_Time="9223372036854775808" Max_Transaction_Waiting_Time="0"/>
			<SSDDevice.TSU.GC_Read_TR_Queue Name="GC_Read_TR_Queue@3@3" No_Of_Transactions_Enqueued="0" No_Of_Transactions_Dequeued="0" Avg_Queue_Length="0.000000" Max_Queue_Length="0" STDev_Queue_Length="0.000000" Avg_Transaction_Waiting_Time="9223372036854775808" Max_Transaction_Waiting_Time="0"/>
			<SSDDevice.TSU.GC_Read_TR_Queue Name="GC_Read_TR_Queue@4@0" No_Of_Transactions_Enqueued="0" No_Of_Transactions_Dequeued="0" Avg_Queue_Length="0.000000" Max_Queue_Length="0" STDev_Queue_Length="0.000000" Avg_Transaction_Waiting_Time="9223372036854775808" Max_Transaction_Waiting_Time="0"/>
			<SSDDevice.TSU.GC_Read_TR_Queue Name="GC_Read_TR_Queue@4@1" No_Of_Transactions_Enqueued="0" No_Of_Transactions_Dequeued="0" Avg_Queue_Length="0.000000" Max_Queue_Length="0" STDev_Queue_Length="0.000000" Avg_Transaction_Waiting_Time="9223372036854775808" Max_Transaction_Waiting_Time="0"/>
			<SSDDevice.TSU.GC_Read_TR_Queue Name="GC_Read_TR_Queue@4@2" No_Of_Transactions_Enqueued="0" No_Of_Transactions_Dequeued="0" Avg_Queue_Length="0.000000" Max_Queue_Length="0" STDev_Queue_Length="0.000000" Avg_Transaction_Waiting_Time="9223372036854775808" Max_Transaction_Waiting_Time="0"/>
			<SSDDevice.TSU.GC_Read_TR_Queue Name="GC_Read_TR_Queue@4@3" No_Of_Transactions_Enqueued="0" No_Of_Transactions_Dequeued="0" Avg_Queue_Length="0.000000" Max_Queue_Length="0" STDev_Queue_Length="0.000000" Avg_Transaction_Waiting_Time="9223372036854775808" Max_Transaction_Waiting_Time="0"/>
			<SSDDevice.TSU.GC_Read_TR_Queue Name="GC_Read_TR_Queue@5@0" No_Of_Transactions_Enqueued="0" No_Of_Transactions_Dequeued="0" Avg_Queue_Length="0.000000" Max_Queue_Length="0" STDev_Queue_Length="0.000000" Avg_Transaction_Waiting_Time="9223372036854775808" Max_Transaction_Waiting_Time="0"/>
			<SSDDevice.TSU.GC_Read_TR_Queue Name="GC_Read_TR_Queue@5@1" No_Of_Transactions_Enqueued="0" No_Of_Transactions_Dequeued="0" Avg_Queue_Length="0.000000" Max_Queue_Length="0" STDev_Queue_Length="0.000000" Avg_Transaction_Waiting_Time="9223372036854775808" Max_Transaction_Waiting_Time="0"/>
			<SSDDevice.TSU.GC_Read_TR_Queue Name="GC_Read_TR_Queue@5@2" No_Of_Transactions_Enqueued="0" No_Of_Transactions_Dequeued="0" Avg_Queue_Length="0.000000" Max_Queue_Length="0" STDev_Queue_Length="0.000000" Avg_Transaction_Waiting_Time="9223372036854775808" Max_Transaction_Waiting_Time="0"/>
			<SSDDevice.TSU.GC_Read_TR_Queue Name="GC_Read_TR_Queue@5@3" No_Of_Transactions_Enqueued="0" No_Of_Transactions_Dequeued="0" Avg_Queue_Length="0.000000" Max_Queue_Length="0" STDev_Queue_Length="0.000000" Avg_Transaction_Waiting_Time="9223372036854775808" Max_Transaction_Waiting_Time="0"/>
			<SSDDevice.TSU.GC_Read_TR_Queue Name="GC_Read_TR_Queue@6@0" No_Of_Transactions_Enqueued="0" No_Of_Transactions_Dequeued="0" Avg_Queue_Length="0.000000" Max_Queue_Length="0" STDev_Queue_Length="0.000000" Avg_Transaction_Waiting_Time="9223372036854775808" Max_Transaction_Waiting_Time="0"/>
			<SSDDevice.TSU.GC_Read_TR_Queue Name="GC_Read_TR_Queue@6@1" No_Of_Transactions_Enqueued="0" No_Of_Transactions_Dequeued="0" Avg_Queue_Length="0.000000" Max_Queue_Length="0" STDev_Queue_Length="0.000000" Avg_Transaction_Waiting_Time="9223372036854775808" Max_Transaction_Waiting_Time="0"/>
			<SSDDevice.TSU.GC_Read_TR_Queue Name="GC_Read_TR_Queue@6@2" No_Of_Transactions_Enqueued="0" No_Of_Transactions_Dequeued="0" Avg_Queue_Length="0.000000" Max_Queue_Length="0" STDev_Queue_Length="0.000000" Avg_Transaction_Waiting_Time="9223372036854775808" Max_Transaction_Waiting_Time="0"/>
			<SSDDevice.TSU.GC_Read_TR_Queue Name="GC_Read_TR_Queue@6@3" No_Of_Transactions_Enqueued="0" No_Of_Transactions_Dequeued="0" Avg_Queue_Length="0.000000" Max_Queue_Length="0" STDev_Queue_Length="0.000000" Avg_Transaction_Waiting_Time="9223372036854775808" Max_Transaction_Waiting_Time="0"/>
			<SSDDevice.TSU.GC_Read_TR_Queue Name="GC_Read_TR_Queue@7@0" No_Of_Transactions_Enqueued="0" No_Of_Transactions_Dequeued="0" Avg_Queue_Length="0.000000" Max_Queue_Length="0" STDev_Queue_Length="0.000000" Avg_Transaction_Waiting_Time="9223372036854775808" Max_Transaction_Waiting_Time="0"/>
			<SSDDevice.TSU.GC_Read_TR_Queue Name="GC_Read_TR_Queue@7@1" No_Of_Transactions_Enqueued="0" No_Of_Transactions_Dequeued="0" Avg_Queue_Length="0.000000" Max_Queue_Length="0" STDev_Queue_Length="0.000000" Avg_Transaction_Waiting_Time="9223372036854775808" Max_Transaction_Waiting_Time="0"/>
			<SSDDevice.TSU.GC_Read_TR_Queue Name="GC_Read_TR_Queue@7@2" No_Of_Transactions_Enqueued="0" No_Of_Transactions_Dequeued="0" Avg_Queue_Length="0.000000" Max_Queue_Length="0" STDev_Queue_Length="0.000000" Avg_Transaction_Waiting_Time="9223372036854775808" Max_Transaction_Waiting_Time="0"/>
			<SSDDevice.TSU.GC_Read_TR_Queue Name="GC_Read_TR_Queue@7@3" No_Of_Transactions_Enqueued="0" No_Of_Transactions_Dequeued="0" Avg_Queue_Length="0.000000" Max_Queue_Length="0" STDev_Queue_Length="0.000000" Avg_Transaction_Waiting_Time="9223372036854775808" Max_Transaction_Waiting_Time="0"/>
			<SSDDevice.TSU.GC_Write_TR_Queue Name="GC_Write_TR_Queue@0@0" No_Of_Transactions_Enqueued="0" No_Of_Transactions_Dequeued="0" Avg_Queue_Length="0.000000" Max_Queue_Length="0" STDev_Queue_Length="0.000000" Avg_Transaction_Waiting_Time="9223372036854775808" Max_Transaction_Waiting_Time="0"/>
			<SSDDevice.TSU.GC_Write_TR_Queue Name="GC_Write_TR_Queue@0@1" No_Of_Transactions_Enqueued="0" No_Of_Transactions_Dequeued="0" Avg_Queue_Length="0.000000" Max_Queue_Length="0" STDev_Queue_Length="0.000000" Avg_Transaction_Waiting_Time="9223372036854775808" Max_Transaction_Waiting_Time="0"/>
			<SSDDevice.TSU.GC_Write_TR_Queue Name="GC_Write_TR_Queue@0@2" No_Of_Transactions_Enqueued="0" No_Of_Transactions_Dequeued="0" Avg_Queue_Length="0.000000" Max_Queue_Length="0" STDev_Queue_Length="0.000000" Avg_Transaction_Waiting_Time="9223372036854775808" Max_Transaction_Waiting_Time="0"/>
			<SSDDevice.TSU.GC_Write_TR_Queue Name="GC_Write_TR_Queue@0@3" No_Of_Transactions_Enqueued="0" No_Of_Transactions_Dequeued="0" Avg_Queue_Length="0.000000" Max_Queue_Length="0" STDev_Queue_Length="0.000000" Avg_Transaction_Waiting_Time="9223372036854775808" Max_Transaction_Waiting_Time="0"/>
			<SSDDevice.TSU.GC_Write_TR_Queue Name="GC_Write_TR_Queue@1@0" No_Of_Transactions_Enqueued="0" No_Of_Transactions_Dequeued="0" Avg_Queue_Length="0.000000" Max_Queue_Length="0" STDev_Queue_Length="0.000000" Avg_Transaction_Waiting_Time="9223372036854775808" Max_Transaction_Waiting_Time="0"/>
			<SSDDevice.TSU.GC_Write_TR_Queue Name="GC_Write_TR_Queue@1@1" No_Of_Transactions_Enqueued="0" No_Of_Transactions_Dequeued="0" Avg_Queue_Length="0.000000" Max_Queue_Length="0" STDev_Queue_Length="0.000000" Avg_Transaction_Waiting_Time="9223372036854775808" Max_Transaction_Waiting_Time="0"/>
			<SSDDevice.TSU.GC_Write_TR_Queue Name="GC_Write_TR_Queue@1@2" No_Of_Transactions_Enqueued="0" No_Of_Transactions_Dequeued="0" Avg_Queue_Length="0.000000" Max_Queue_Length="0" STDev_Queue_Length="0.000000" Avg_Transaction_Waiting_Time="9223372036854775808" Max_Transaction_Waiting_Time="0"/>
			<SSDDevice.TSU.GC_Write_TR_Queue Name="GC_Write_TR_Queue@1@3" No_Of_Transactions_Enqueued="0" No_Of_Transactions_Dequeued="0" Avg_Queue_Length="0.000000" Max_Queue_Length="0" STDev_Queue_Length="0.000000" Avg_Transaction_Waiting_Time="9223372036854775808" Max_Transaction_Waiting_Time="0"/>
			<SSDDevice.TSU.GC_Write_TR_Queue Name="GC_Write_TR_Queue@2@0" No_Of_Transactions_Enqueued="0" No_Of_Transactions_Dequeued="0" Avg_Queue_Length="0.000000" Max_Queue_Length="0" STDev_Queue_Length="0.000000" Avg_Transaction_Waiting_Time="9223372036854775808" Max_Transaction_Waiting_Time="0"/>
			<SSDDevice.TSU.GC_Write_TR_Queue Name="GC_Write_TR_Queue@2@1" No_Of_Transactions_Enqueued="0" No_Of_Transactions_Dequeued="0" Avg_Queue_Length="0.000000" Max_Queue_Length="0" STDev_Queue_Length="0.000000" Avg_Transaction_Waiting_Time="9223372036854775808" Max_Transaction_Waiting_Time="0"/>
			<SSDDevice.TSU.GC_Write_TR_Queue Name="GC_Write_TR_Queue@2@2" No_Of_Transactions_Enqueued="0" No_Of_Transactions_Dequeued="0" Avg_Queue_Length="0.000000" Max_Queue_Length="0" STDev_Queue_Length="0.000000" Avg_Transaction_Waiting_Time="9223372036854775808" Max_Transaction_Waiting_Time="0"/>
			<SSDDevice.TSU.GC_Write_TR_Queue Name="GC_Write_TR_Queue@2@3" No_Of_Transactions_Enqueued="0" No_Of_Transactions_Dequeued="0" Avg_Queue_Length="0.000000" Max_Queue_Length="0" STDev_Queue_Length="0.000000" Avg_Transaction_Waiting_Time="9223372036854775808" Max_Transaction_Waiting_Time="0"/>
			<SSDDevice.TSU.GC_Write_TR_Queue Name="GC_Write_TR_Queue@3@0" No_Of_Transactions_Enqueued="0" No_Of_Transactions_Dequeued="0" Avg_Queue_Length="0.000000" Max_Queue_Length="0" STDev_Queue_Length="0.000000" Avg_Transaction_Waiting_Time="9223372036854775808" Max_Transaction_Waiting_Time="0"/>
			<SSDDevice.TSU.GC_Write_TR_Queue Name="GC_Write_TR_Queue@3@1" No_Of_Transactions_Enqueued="0" No_Of_Transactions_Dequeued="0" Avg_Queue_Length="0.000000" Max_Queue_Length="0" STDev_Queue_Length="0.000000" Avg_Transaction_Waiting_Time="9223372036854775808" Max_Transaction_Waiting_Time="0"/>
			<SSDDevice.TSU.GC_Write_TR_Queue Name="GC_Write_TR_Queue@3@2" No_Of_Transactions_Enqueued="0" No_Of_Transactions_Dequeued="0" Avg_Queue_Length="0.000000" Max_Queue_Length="0" STDev_Queue_Length="0.000000" Avg_Transaction_Waiting_Time="9223372036854775808" Max_Transaction_Waiting_Time="0"/>
			<SSDDevice.TSU.GC_Write_TR_Queue Name="GC_Write_TR_Queue@3@3" No_Of_Transactions_Enqueued="0" No_Of_Transactions_Dequeued="0" Avg_Queue_Length="0.000000" Max_Queue_Length="0" STDev_Queue_Length="0.000000" Avg_Transaction_Waiting_Time="9223372036854775808" Max_Transaction_Waiting_Time="0"/>
			<SSDDevice.TSU.GC_Write_TR_Queue Name="GC_Write_TR_Queue@4@0" No_Of_Transactions_Enqueued="0" No_Of_Transactions_Dequeued="0" Avg_Queue_Length="0.000000" Max_Queue_Length="0" STDev_Queue_Length="0.000000" Avg_Transaction_Waiting_Time="9223372036854775808" Max_Transaction_Waiting_Time="0"/>
			<SSDDevice.TSU.GC_Write_TR_Queue Name="GC_Write_TR_Queue@4@1" No_Of_Transactions_Enqueued="0" No_Of_Transactions_Dequeued="0" Avg_Queue_Length="0.000000" Max_Queue_Length="0" STDev_Queue_Length="0.000000" Avg_Transaction_Waiting_Time="9223372036854775808" Max_Transaction_Waiting_Time="0"/>
			<SSDDevice.TSU.GC_Write_TR_Queue Name="GC_Write_TR_Queue@4@2" No_Of_Transactions_Enqueued="0" No_Of_Transactions_Dequeued="0" Avg_Queue_Length="0.000000" Max_Queue_Length="0" STDev_Queue_Length="0.000000" Avg_Transaction_Waiting_Time="9223372036854775808" Max_Transaction_Waiting_Time="0"/>
			<SSDDevice.TSU.GC_Write_TR_Queue Name="GC_Write_TR_Queue@4@3" No_Of_Transactions_Enqueued="0" No_Of_Transactions_Dequeued="0" Avg_Queue_Length="0.000000" Max_Queue_Length="0" STDev_Queue_Length="0.000000" Avg_Transaction_Waiting_Time="9223372036854775808" Max_Transaction_Waiting_Time="0"/>
			<SSDDevice.TSU.GC_Write_TR_Queue Name="GC_Write_TR_Queue@5@0" No_Of_Transactions_Enqueued="0" No_Of_Transactions_Dequeued="0" Avg_Queue_Length="0.000000" Max_Queue_Length="0" STDev_Queue_Length="0.000000" Avg_Transaction_Waiting_Time="9223372036854775808" Max_Transaction_Waiting_Time="0"/>
			<SSDDevice.TSU.GC_Write_TR_Queue Name="GC_Write_TR_Queue@5@1" No_Of_Transactions_Enqueued="0" No_Of_Transactions_Dequeued="0" Avg_Queue_Length="0.000000" Max_Queue_Length="0" STDev_Queue_Length="0.000000" Avg_Transaction_Waiting_Time="9223372036854775808" Max_Transaction_Waiting_Time="0"/>
			<SSDDevice.TSU.GC_Write_TR_Queue Name="GC_Write_TR_Queue@5@2" No_Of_Transactions_Enqueued="0" No_Of_Transactions_Dequeued="0" Avg_Queue_Length="0.000000" Max_Queue_Length="0" STDev_Queue_Length="0.000000" Avg_Transaction_Waiting_Time="9223372036854775808" Max_Transaction_Waiting_Time="0"/>
			<SSDDevice.TSU.GC_Write_TR_Queue Name="GC_Write_TR_Queue@5@3" No_Of_Transactions_Enqueued="0" No_Of_Transactions_Dequeued="0" Avg_Queue_Length="0.000000" Max_Queue_Length="0" STDev_Queue_Length="0.000000" Avg_Transaction_Waiting_Time="9223372036854775808" Max_Transaction_Waiting_Time="0"/>
			<SSDDevice.TSU.GC_Write_TR_Queue Name="GC_Write_TR_Queue@6@0" No_Of_Transactions_Enqueued="0" No_Of_Transactions_Dequeued="0" Avg_Queue_Length="0.000000" Max_Queue_Length="0" STDev_Queue_Length="0.000000" Avg_Transaction_Waiting_Time="9223372036854775808" Max_Transaction_Waiting_Time="0"/>
			<SSDDevice.TSU.GC_Write_TR_Queue Name="GC_Write_TR_Queue@6@1" No_Of_Transactions_Enqueued="0" No_Of_Transactions_Dequeued="0" Avg_Queue_Length="0.000000" Max_Queue_Length="0" STDev_Queue_Length="0.000000" Avg_Transaction_Waiting_Time="9223372036854775808" Max_Transaction_Waiting_Time="0"/>
			<SSDDevice.TSU.GC_Write_TR_Queue Name="GC_Write_TR_Queue@6@2" No_Of_Transactions_Enqueued="0" No_Of_Transactions_Dequeued="0" Avg_Queue_Length="0.000000" Max_Queue_Length="0" STDev_Queue_Length="0.000000" Avg_Transaction_Waiting_Time="9223372036854775808" Max_Transaction_Waiting_Time="0"/>
			<SSDDevice.TSU.GC_Write_TR_Queue Name="GC_Write_TR_Queue@6@3" No_Of_Transactions_Enqueued="0" No_Of_Transactions_Dequeued="0" Avg_Queue_Length="0.000000" Max_Queue_Length="0" STDev_Queue_Length="0.000000" Avg_Transaction_Waiting_Time="9223372036854775808" Max_Transaction_Waiting_Time="0"/>
			<SSDDevice.TSU.GC_Write_TR_Queue Name="GC_Write_TR_Queue@7@0" No_Of_Transactions_Enqueued="0" No_Of_Transactions_Dequeued="0" Avg_Queue_Length="0.000000" Max_Queue_Length="0" STDev_Queue_Length="0.000000" Avg_Transaction_Waiting_Time="9223372036854775808" Max_Transaction_Waiting_Time="0"/>
			<SSDDevice.TSU.GC_Write_TR_Queue Name="GC_Write_TR_Queue@7@1" No_Of_Transactions_Enqueued="0" No_Of_Transactions_Dequeued="0" Avg_Queue_Length="0.000000" Max_Queue_Length="0" STDev_Queue_Length="0.000000" Avg_Transaction_Waiting_Time="9223372036854775808" Max_Transaction_Waiting_Time="0"/>
			<SSDDevice.TSU.GC_Write_TR_Queue Name="GC_Write_TR_Queue@7@2" No_Of_Transactions_Enqueued="0" No_Of_Transactions_Dequeued="0" Avg_Queue_Length="0.000000" Max_Queue_Length="0" STDev_Queue_Length="0.000000" Avg_Transaction_Waiting_Time="9223372036854775808" Max_Transaction_Waiting_Time="0"/>
			<SSDDevice.TSU.GC_Write_TR_Queue Name="GC_Write_TR_Queue@7@3" No_Of_Transactions_Enqueued="0" No_Of_Transactions_Dequeued="0" Avg_Queue_Length="0.000000" Max_Queue_Length="0" STDev_Queue_Length="0.000000" Avg_Transaction_Waiting_Time="9223372036854775808" Max_Transaction_Waiting_Time="0"/>
			<SSDDevice.TSU.GC_Erase_TR_Queue Name="GC_Erase_TR_Queue@0@0" No_Of_Transactions_Enqueued="0" No_Of_Transactions_Dequeued="0" Avg_Queue_Length="0.000000" Max_Queue_Length="0" STDev_Queue_Length="0.000000" Avg_Transaction_Waiting_Time="9223372036854775808" Max_Transaction_Waiting_Time="0"/>
			<SSDDevice.TSU.GC_Erase_TR_Queue Name="GC_Erase_TR_Queue@0@1" No_Of_Transactions_Enqueued="0" No_Of_Transactions_Dequeued="0" Avg_Queue_Length="0.000000" Max_Queue_Length="0" STDev_Queue_Length="0.000000" Avg_Transaction_Waiting_Time="9223372036854775808" Max_Transaction_Waiting_Time="0"/>
			<SSDDevice.TSU.GC_Erase_TR_Queue Name="GC_Erase_TR_Queue@0@2" No_Of_Transactions_Enqueued="0" No_Of_Transactions_Dequeued="0" Avg_Queue_Length="0.000000" Max_Queue_Length="0" STDev_Queue_Length="0.000000" Avg_Transaction_Waiting_Time="9223372036854775808" Max_Transaction_Waiting_Time="0"/>
			<SSDDevice.TSU.GC_Erase_TR_Queue Name="GC_Erase_TR_Queue@0@3" No_Of_Transactions_Enqueued="0" No_Of_Transactions_Dequeued="0" Avg_Queue_Length="0.000000" Max_Queue_Length="0" STDev_Queue_Length="0.000000" Avg_Transaction_Waiting_Time="9223372036854775808" Max_Transaction_Waiting_Time="0"/>
			<SSDDevice.TSU.GC_Erase_TR_Queue Name="GC_Erase_TR_Queue@1@0" No_Of_Transactions_Enqueued="0" No_Of_Transactions_Dequeued="0" Avg_Queue_Length="0.000000" Max_Queue_Length="0" STDev_Queue_Length="0.000000" Avg_Transaction_Waiting_Time="9223372036854775808" Max_Transaction_Waiting_Time="0"/>
			<SSDDevice.TSU.GC_Erase_TR_Queue Name="GC_Erase_TR_Queue@1@1" No_Of_Transactions_Enqueued="0" No_Of_Transactions_Dequeued="0" Avg_Queue_Length="0.000000" Max_Queue_Length="0" STDev_Queue_Length="0.000000" Avg_Transaction_Waiting_Time="9223372036854775808" Max_Transaction_Waiting_Time="0"/>
			<SSDDevice.TSU.GC_Erase_TR_Queue Name="GC_Erase_TR_Queue@1@2" No_Of_Transactions_Enqueued="0" No_Of_Transactions_Dequeued="0" Avg_Queue_Length="0.000000" Max_Queue_Length="0" STDev_Queue_Length="0.000000" Avg_Transaction_Waiting_Time="9223372036854775808" Max_Transaction_Waiting_Time="0"/>
			<SSDDevice.TSU.GC_Erase_TR_Queue Name="GC_Erase_TR_Queue@1@3" No_Of_Transactions_Enqueued="0" No_Of_Transactions_Dequeued="0" Avg_Queue_Length="0.000000" Max_Queue_Length="0" STDev_Queue_Length="0.000000" Avg_Transaction_Waiting_Time="9223372036854775808" Max_Transaction_Waiting_Time="0"/>
			<SSDDevice.TSU.GC_Erase_TR_Queue Name="GC_Erase_TR_Queue@2@0" No_Of_Transactions_Enqueued="0" No_Of_Transactions_Dequeued="0" Avg_Queue_Length="0.000000" Max_Queue_Length="0" STDev_Queue_Length="0.000000" Avg_Transaction_Waiting_Time="9223372036854775808" Max_Transaction_Waiting_Time="0"/>
			<SSDDevice.TSU.GC_Erase_TR_Queue Name="GC_Erase_TR_Queue@2@1" No_Of_Transactions_Enqueued="0" No_Of_Transactions_Dequeued="0" Avg_Queue_Length="0.000000" Max_Queue_Length="0" STDev_Queue_Length="0.000000" Avg_Transaction_Waiting_Time="9223372036854775808" Max_Transaction_Waiting_Time="0"/>
			<SSDDevice.TSU.GC_Erase_TR_Queue Name="GC_Erase_TR_Queue@2@2" No_Of_Transactions_Enqueued="0" No_Of_Transactions_Dequeued="0" Avg_Queue_Length="0.000000" Max_Queue_Length="0" STDev_Queue_Length="0.000000" Avg_Transaction_Waiting_Time="9223372036854775808" Max_Transaction_Waiting_Time="0"/>
			<SSDDevice.TSU.GC_Erase_TR_Queue Name="GC_Erase_TR_Queue@2@3" No_Of_Transactions_Enqueued="0" No_Of_Transactions_Dequeued="0" Avg_Queue_Length="0.000000" Max_Queue_Length="0" STDev_Queue_Length="0.000000" Avg_Transaction_Waiting_Time="9223372036854775808" Max_Transaction_Waiting_Time="0"/>
			<SSDDevice.TSU.GC_Erase_TR_Queue Name="GC_Erase_TR_Queue@3@0" No_Of_Transactions_Enqueued="0" No_Of_Transactions_Dequeued="0" Avg_Queue_Length="0.000000" Max_Queue_Length="0" STDev_Queue_Length="0.000000" Avg_Transaction_Waiting_Time="9223372036854775808" Max_Transaction_Waiting_Time="0"/>
			<SSDDevice.TSU.GC_Erase_TR_Queue Name="GC_Erase_TR_Queue@3@1" No_Of_Transactions_Enqueued="0" No_Of_Transactions_Dequeued="0" Avg_Queue_Length="0.000000" Max_Queue_Length="0" STDev_Queue_Length="0.000000" Avg_Transaction_Waiting_Time="9223372036854775808" Max_Transaction_Waiting_Time="0"/>
			<SSDDevice.TSU.GC_Erase_TR_Queue Name="GC_Erase_TR_Queue@3@2" No_Of_Transactions_Enqueued="0" No_Of_Transactions_Dequeued="0" Avg_Queue_Length="0.000000" Max_Queue_Length="0" STDev_Queue_Length="0.000000" Avg_Transaction_Waiting_Time="9223372036854775808" Max_Transaction_Waiting_Time="0"/>
			<SSDDevice.TSU.GC_Erase_TR_Queue Name="GC_Erase_TR_Queue@3@3" No_Of_Transactions_Enqueued="0" No_Of_Transactions_Dequeued="0" Avg_Queue_Length="0.000000" Max_Queue_Length="0" STDev_Queue_Length="0.000000" Avg_Transaction_Waiting_Time="9223372036854775808" Max_Transaction_Waiting_Time="0"/>
			<SSDDevice.TSU.GC_Erase_TR_Queue Name="GC_Erase_TR_Queue@4@0" No_Of_Transactions_Enqueued="0" No_Of_Transactions_Dequeued="0" Avg_Queue_Length="0.000000" Max_Queue_Length="0" STDev_Queue_Length="0.000000" Avg_Transaction_Waiting_Time="9223372036854775808" Max_Transaction_Waiting_Time="0"/>
			<SSDDevice.TSU.GC_Erase_TR_Queue Name="GC_Erase_TR_Queue@4@1" No_Of_Transactions_Enqueued="0" No_Of_Transactions_Dequeued="0" Avg_Queue_Length="0.000000" Max_Queue_Length="0" STDev_Queue_Length="0.000000" Avg_Transaction_Waiting_Time="9223372036854775808" Max_Transaction_Waiting_Time="0"/>
			<SSDDevice.TSU.GC_Erase_TR_Queue Name="GC_Erase_TR_Queue@4@2" No_Of_Transactions_Enqueued="0" No_Of_Transactions_Dequeued="0" Avg_Queue_Length="0.000000" Max_Queue_Length="0" STDev_Queue_Length="0.000000" Avg_Transaction_Waiting_Time="9223372036854775808" Max_Transaction_Waiting_Time="0"/>
			<SSDDevice.TSU.GC_Erase_TR_Queue Name="GC_Erase_TR_Queue@4@3" No_Of_Transactions_Enqueued="0" No_Of_Transactions_Dequeued="0" Avg_Queue_Length="0.000000" Max_Queue_Length="0" STDev_Queue_Length="0.000000" Avg_Transaction_Waiting_Time="9223372036854775808" Max_Transaction_Waiting_Time="0"/>
			<SSDDevice.TSU.GC_Erase_TR_Queue Name="GC_Erase_TR_Queue@5@0" No_Of_Transactions_Enqueued="0" No_Of_Transactions_Dequeued="0" Avg_Queue_Length="0.000000" Max_Queue_Length="0" STDev_Queue_Length="0.000000" Avg_Transaction_Waiting_Time="9223372036854775808" Max_Transaction_Waiting_Time="0"/>
			<SSDDevice.TSU.GC_Erase_TR_Queue Name="GC_Erase_TR_Queue@5@1" No_Of_Transactions_Enqueued="0" No_Of_Transactions_Dequeued="0" Avg_Queue_Length="0.000000" Max_Queue_Length="0" STDev_Queue_Length="0.000000" Avg_Transaction_Waiting_Time="9223372036854775808" Max_Transaction_Waiting_Time="0"/>
			<SSDDevice.TSU.GC_Erase_TR_Queue Name="GC_Erase_TR_Queue@5@2" No_Of_Transactions_Enqueued="0" No_Of_Transactions_Dequeued="0" Avg_Queue_Length="0.000000" Max_Queue_Length="0" STDev_Queue_Length="0.000000" Avg_Transaction_Waiting_Time="9223372036854775808" Max_Transaction_Waiting_Time="0"/>
			<SSDDevice.TSU.GC_Erase_TR_Queue Name="GC_Erase_TR_Queue@5@3" No_Of_Transactions_Enqueued="0" No_Of_Transactions_Dequeued="0" Avg_Queue_Length="0.000000" Max_Queue_Length="0" STDev_Queue_Length="0.000000" Avg_Transaction_Waiting_Time="9223372036854775808" Max_Transaction_Waiting_Time="0"/>
			<SSDDevice.TSU.GC_Erase_TR_Queue Name="GC_Erase_TR_Queue@6@0" No_Of_Transactions_Enqueued="0" No_Of_Transactions_Dequeued="0" Avg_Queue_Length="0.000000" Max_Queue_Length="0" STDev_Queue_Length="0.000000" Avg_Transaction_Waiting_Time="9223372036854775808" Max_Transaction_Waiting_Time="0"/>
			<SSDDevice.TSU.GC_Erase_TR_Queue Name="GC_Erase_TR_Queue@6@1" No_Of_Transactions_Enqueued="0" No_Of_Transactions_Dequeued="0" Avg_Queue_Length="0.000000" Max_Queue_Length="0" STDev_Queue_Length="0.000000" Avg_Transaction_Waiting_Time="9223372036854775808" Max_Transaction_Waiting_Time="0"/>
			<SSDDevice.TSU.GC_Erase_TR_Queue Name="GC_Erase_TR_Queue@6@2" No_Of_Transactions_Enqueued="0" No_Of_Transactions_Dequeued="0" Avg_Queue_Length="0.000000" Max_Queue_Length="0" STDev_Queue_Length="0.000000" Avg_Transaction_Waiting_Time="9223372036854775808" Max_Transaction_Waiting_Time="0"/>
			<SSDDevice.TSU.GC_Erase_TR_Queue Name="GC_Erase_TR_Queue@6@3" No_Of_Transactions_Enqueued="0" No_Of_Transactions_Dequeued="0" Avg_Queue_Length="0.000000" Max_Queue_Length="0" STDev_Queue_Length="0.000000" Avg_Transaction_Waiting_Time="9223372036854775808" Max_Transaction_Waiting_Time="0"/>
			<SSDDevice.TSU.GC_Erase_TR_Queue Name="GC_Erase_TR_Queue@7@0" No_Of_Transactions_Enqueued="0" No_Of_Transactions_Dequeued="0" Avg_Queue_Length="0.000000" Max_Queue_Length="0" STDev_Queue_Length="0.000000" Avg_Transaction_Waiting_Time="9223372036854775808" Max_Transaction_Waiting_Time="0"/>
			<SSDDevice.TSU.GC_Erase_TR_Queue Name="GC_Erase_TR_Queue@7@1" No_Of_Transactions_Enqueued="0" No_Of_Transactions_Dequeued="0" Avg_Queue_Length="0.000000" Max_Queue_Length="0" STDev_Queue_Length="0.000000" Avg_Transaction_Waiting_Time="9223372036854775808" Max_Transaction_Waiting_Time="0"/>
			<SSDDevice.TSU.GC_Erase_TR_Queue Name="GC_Erase_TR_Queue@7@2" No_Of_Transactions_Enqueued="0" No_Of_Transactions_Dequeued="0" Avg_Queue_Length="0.000000" Max_Queue_Length="0" STDev_Queue_Length="0.000000" Avg_Transaction_Waiting_Time="9223372036854775808" Max_Transaction_Waiting_Time="0"/>
			<SSDDevice.TSU.GC_Erase_TR_Queue Name="GC_Erase_TR_Queue@7@3" No_Of_Transactions_Enqueued="0" No_Of_Transactions_Dequeued="0" Avg_Queue_Length="0.000000" Max_Queue_Length="0" STDev_Queue_Length="0.000000" Avg_Transaction_Waiting_Time="9223372036854775808" Max_Transaction_Waiting_Time="0"/>
		</SSDDevice.TSU>
		<SSDDevice.FlashChips ID="@0@0" Fraction_of_Time_in_Execution="0.188593" Fraction_of_Time_in_DataXfer="0.031799" Fraction_of_Time_in_DataXfer_and_Execution="0.000008" Fraction_of_Time_Idle="0.968193"/>
		<SSDDevice.FlashChips ID="@0@1" Fraction_of_Time_in_Execution="0.191579" Fraction_of_Time_in_DataXfer="0.032307" Fraction_of_Time_in_DataXfer_and_Execution="0.000009" Fraction_of_Time_Idle="0.967684"/>
		<SSDDevice.FlashChips ID="@0@2" Fraction_of_Time_in_Execution="0.000000" Fraction_of_Time_in_DataXfer="0.000000" Fraction_of_Time_in_DataXfer_and_Execution="0.000000" Fraction_of_Time_Idle="1.000000"/>
		<SSDDevice.FlashChips ID="@0@3" Fraction_of_Time_in_Execution="0.000000" Fraction_of_Time_in_DataXfer="0.000000" Fraction_of_Time_in_DataXfer_and_Execution="0.000000" Fraction_of_Time_Idle="1.000000"/>
		<SSDDevice.FlashChips ID="@1@0" Fraction_of_Time_in_Execution="0.186425" Fraction_of_Time_in_DataXfer="0.031426" Fraction_of_Time_in_DataXfer_and_Execution="0.000008" Fraction_of_Time_Idle="0.968567"/>
		<SSDDevice.FlashChips ID="@1@1" Fraction_of_Time_in_Execution="0.191024" Fraction_of_Time_in_DataXfer="0.032183" Fraction_of_Time_in_DataXfer_and_Execution="0.000007" Fraction_of_Time_Idle="0.967810"/>
		<SSDDevice.FlashChips ID="@1@2" Fraction_of_Time_in_Execution="0.000000" Fraction_of_Time_in_DataXfer="0.000000" Fraction_of_Time_in_DataXfer_and_Execution="0.000000" Fraction_of_Time_Idle="1.000000"/>
		<SSDDevice.FlashChips ID="@1@3" Fraction_of_Time_in_Execution="0.000000" Fraction_of_Time_in_DataXfer="0.000000" Fraction_of_Time_in_DataXfer_and_Execution="0.000000" Fraction_of_Time_Idle="1.000000"/>
		<SSDDevice.FlashChips ID="@2@0" Fraction_of_Time_in_Execution="0.187911" Fraction_of_Time_in_DataXfer="0.031672" Fraction_of_Time_in_DataXfer_and_Execution="0.000008" Fraction_of_Time_Idle="0.968320"/>
		<SSDDevice.FlashChips ID="@2@1" Fraction_of_Time_in_Execution="0.187363" Fraction_of_Time_in_DataXfer="0.031584" Fraction_of_Time_in_DataXfer_and_Execution="0.000008" Fraction_of_Time_Idle="0.968408"/>
		<SSDDevice.FlashChips ID="@2@2" Fraction_of_Time_in_Execution="0.000000" Fraction_of_Time_in_DataXfer="0.000000" Fraction_of_Time_in_DataXfer_and_Execution="0.000000" Fraction_of_Time_Idle="1.000000"/>
		<SSDDevice.FlashChips ID="@2@3" Fraction_of_Time_in_Execution="0.000000" Fraction_of_Time_in_DataXfer="0.000000" Fraction_of_Time_in_DataXfer_and_Execution="0.000000" Fraction_of_Time_Idle="1.000000"/>
		<SSDDevice.FlashChips ID="@3@0" Fraction_of_Time_in_Execution="0.189590" Fraction_of_Time_in_DataXfer="0.031914" Fraction_of_Time_in_DataXfer_and_Execution="0.000006" Fraction_of_Time_Idle="0.968081"/>
		<SSDDevice.FlashChips ID="@3@1" Fraction_of_Time_in_Execution="0.190588" Fraction_of_Time_in_DataXfer="0.032109" Fraction_of_Time_in_DataXfer_and_Execution="0.000007" Fraction_of_Time_Idle="0.967884"/>
		<SSDDevice.FlashChips ID="@3@2" Fraction_of_Time_in_Execution="0.000000" Fraction_of_Time_in_DataXfer="0.000000" Fraction_of_Time_in_DataXfer_and_Execution="0.000000" Fraction_of_Time_Idle="1.000000"/>
		<SSDDevice.FlashChips ID="@3@3" Fraction_of_Time_in_Execution="0.000000" Fraction_of_Time_in_DataXfer="0.000000" Fraction_of_Time_in_DataXfer_and_Execution="0.000000" Fraction_of_Time_Idle="1.000000"/>
		<SSDDevice.FlashChips ID="@4@0" Fraction_of_Time_in_Execution="0.190153" Fraction_of_Time_in_DataXfer="0.032010" Fraction_of_Time_in_DataXfer_and_Execution="0.000006" Fraction_of_Time_Idle="0.967984"/>
		<SSDDevice.FlashChips ID="@4@1" Fraction_of_Time_in_Execution="0.189673" Fraction_of_Time_in_DataXfer="0.031937" Fraction_of_Time_in_DataXfer_and_Execution="0.000006" Fraction_of_Time_Idle="0.968056"/>
		<SSDDevice.FlashChips ID="@4@2" Fraction_of_Time_in_Execution="0.000000" Fraction_of_Time_in_DataXfer="0.000000" Fraction_of_Time_in_DataXfer_and_Execution="0.000000" Fraction_of_Time_Idle="1.000000"/>
		<SSDDevice.FlashChips ID="@4@3" Fraction_of_Time_in_Execution="0.000000" Fraction_of_Time_in_DataXfer="0.000000" Fraction_of_Time_in_DataXfer_and_Execution="0.000000" Fraction_of_Time_Idle="1.000000"/>
		<SSDDevice.FlashChips ID="@5@0" Fraction_of_Time_in_Execution="0.188585" Fraction_of_Time_in_DataXfer="0.031771" Fraction_of_Time_in_DataXfer_and_Execution="0.000007" Fraction_of_Time_Idle="0.968222"/>
		<SSDDevice.FlashChips ID="@5@1" Fraction_of_Time_in_Execution="0.187723" Fraction_of_Time_in_DataXfer="0.031624" Fraction_of_Time_in_DataXfer_and_Execution="0.000007" Fraction_of_Time_Idle="0.968369"/>
		<SSDDevice.FlashChips ID="@5@2" Fraction_of_Time_in_Execution="0.000000" Fraction_of_Time_in_DataXfer="0.000000" Fraction_of_Time_in_DataXfer_and_Execution="0.000000" Fraction_of_Time_Idle="1.000000"/>
		<SSDDevice.FlashChips ID="@5@3" Fraction_of_Time_in_Execution="0.000000" Fraction_of_Time_in_DataXfer="0.000000" Fraction_of_Time_in_DataXfer_and_Execution="0.000000" Fraction_of_Time_Idle="1.000000"/>
		<SSDDevice.FlashChips ID="@6@0" Fraction_of_Time_in_Execution="0.189688" Fraction_of_Time_in_DataXfer="0.031963" Fraction_of_Time_in_DataXfer_and_Execution="0.000007" Fraction_of_Time_Idle="0.968030"/>
		<SSDDevice.FlashChips ID="@6@1" Fraction_of_Time_in_Execution="0.189396" Fraction_of_Time_in_DataXfer="0.031916" Fraction_of_Time_in_DataXfer_and_Execution="0.000007" Fraction_of_Time_Idle="0.968077"/>
		<SSDDevice.FlashChips ID="@6@2" Fraction_of_Time_in_Execution="0.000000" Fraction_of_Time_in_DataXfer="0.000000" Fraction_of_Time_in_DataXfer_and_Execution="0.000000" Fraction_of_Time_Idle="1.000000"/>
		<SSDDevice.FlashChips ID="@6@3" Fraction_of_Time_in_Execution="0.000000" Fraction_of_Time_in_DataXfer="0.000000" Fraction_of_Time_in_DataXfer_and_Execution="0.000000" Fraction_of_Time_Idle="1.000000"/>
		<SSDDevice.FlashChips ID="@7@0" Fraction_of_Time_in_Execution="0.188353" Fraction_of_Time_in_DataXfer="0.031726" Fraction_of_Time_in_DataXfer_and_Execution="0.000007" Fraction_of_Time_Idle="0.968267"/>
		<SSDDevice.FlashChips ID="@7@1" Fraction_of_Time_in_Execution="0.188706" Fraction_of_Time_in_DataXfer="0.031800" Fraction_of_Time_in_DataXfer_and_Execution="0.000007" Fraction_of_Time_Idle="0.968192"/>
		<SSDDevice.FlashChips ID="@7@2" Fraction_of_Time_in_Execution="0.000000" Fraction_of_Time_in_DataXfer="0.000000" Fraction_of_Time_in_DataXfer_and_Execution="0.000000" Fraction_of_Time_Idle="1.000000"/>
		<SSDDevice.FlashChips ID="@7@3" Fraction_of_Time_in_Execution="0.000000" Fraction_of_Time_in_DataXfer="0.000000" Fraction_of_Time_in_DataXfer_and_Execution="0.000000" Fraction_of_Time_Idle="1.000000"/>
	</SSDDevice>
</MQSim_Results>
